microwave.v
`include "BCD_encoder/contador/counter.v"
`include "BCD_encoder/encoder/encoder.v"
`include "BCD_encoder/frequency_divider/fdivider.v"
`include "BCD_encoder/mux/mux.v"

`include "CONTROLE/magnetron/magnetron_logic.v"
`include "CONTROLE/latch/latch_SR.v"

`include "TIMER/counter_mod_6/mod6.v"
`include "TIMER/counter_mod_10/mod10.v"


module microwave(
    input wire [9:0] keys,
    input wire startn, stopn, clearn, door_closed, clock,
    output wire mag_on,
    output wire [6:0] ssec_ones,
    output wire [6:0] ssec_tens,
    output wire [6:0] smin
);

    // fios auxiliares
    wire timer_done_wire;
    wire [3:0] min_wire, sec_tens_wire, sec_ones_wire;
    wire mag_on_wire;
    wire loadn_wire;
    wire [3:0] digit_carrier;
    wire clock_carrier;

    assign mag_on = mag_on_wire; // saída do estado do magnetron

    // conexões
    magnetron_control mag_control(
        //inputs
        .startn(startn),
        .stopn(stopn), 
        .clearn(clearn),
        .door_closed(door_closed),
        .timer_done(timer_done_wire),
        //outputs
        .Q(mag_on_wire)
    );

    c_input keypad(
        //inputs
        .keys(keys),
        .enable(mag_on_wire), 
        .clock(clock),
        //outputs
        .Digit(digit_carrier),
        .loadn(loadn_wire), 
        .pgt_out(clock_carrier)
    );

    timer timer1(
        //inputs
        .clearn(clearn), 
        .loadn(loadn_wire),
        .clock(clock_carrier),
        .enable(mag_on_wire),
        .data(digit_carrier),
        //outputs
        .sec_ones(sec_ones_wire), 
        .sec_tens(sec_tens_wire),
        .mins(min_wire),
        .zero(timer_done_wire)
    );

    decB2SSD decoder(
        //inputs
        .bsec_ones(sec_ones_wire),
        .bsec_tens(sec_tens_wire),
        .bmin(min_wire),
        //outputs
        .ssec_ones(ssec_ones),
        .ssec_tens(ssec_tens),
        .smin(smin)

    );

endmodule

// módulos auxiliares

module decB2SSD(bsec_ones, bsec_tens, bmin, ssec_ones, ssec_tens, smin);

     //inputs/outputs 
    input [3:0] bsec_ones;
    input [3:0] bsec_tens;
    input [3:0] bmin;
    output reg [6:0] ssec_ones;
    output reg [6:0] ssec_tens;
    output reg [6:0] smin;

    // bcd to seven_segments decoder, segments are active-high

    //bloco always para converter os bcd's em SSD's
    always @(bsec_ones, bsec_tens, bmin)
    begin

        case (bmin) //case statement
            0 : smin = 7'b0000000; // apaga sempre que for 0
            1 : smin = 7'b0110000;
            2 : smin = 7'b1101101;
            3 : smin = 7'b1111001;
            4 : smin = 7'b0110011;
            5 : smin = 7'b1011011;
            6 : smin = 7'b0011111;
            7 : smin = 7'b1110000;
            8 : smin = 7'b1111111;
            9 : smin = 7'b1110011;
            //caso nao receba nenhuma dígito decimal desliga todos os segmentos.
            default : smin = 7'b0000000; 
        endcase

        case (bsec_ones) //case statement
            0 : ssec_ones = 7'b1111110;
            1 : ssec_ones = 7'b0110000;
            2 : ssec_ones = 7'b1101101;
            3 : ssec_ones = 7'b1111001;
            4 : ssec_ones = 7'b0110011;
            5 : ssec_ones = 7'b1011011;
            6 : ssec_ones = 7'b0011111;
            7 : ssec_ones = 7'b1110000;
            8 : ssec_ones = 7'b1111111;
            9 : ssec_ones = 7'b1110011;
            //caso nao receba nenhuma dígito decimal desliga todos os segmentos.
            default : ssec_ones = 7'b0000000; 
        endcase

        case (bsec_tens) //case statement
            0 : ssec_tens = 7'b1111110;
            1 : ssec_tens = 7'b0110000;
            2 : ssec_tens = 7'b1101101;
            3 : ssec_tens = 7'b1111001;
            4 : ssec_tens = 7'b0110011;
            5 : ssec_tens = 7'b1011011;
            6 : ssec_tens = 7'b0011111;
            7 : ssec_tens = 7'b1110000;
            8 : ssec_tens = 7'b1111111;
            9 : ssec_tens = 7'b1110011;
            //caso nao receba nenhuma dígito decimal desliga todos os segmentos.
            default : ssec_tens = 7'b0000000; 
        endcase

        // teste para zeros à esquerda
        if ((bmin == 0) && (bsec_tens == 0))
            begin
                ssec_tens = 7'b0000000;

                if (bsec_ones == 0)
                    begin
                        ssec_ones = 7'b0000000;
                    end
            end
    end


    //repetindo para todos os casos

endmodule

module c_input(
    input wire [9:0] keys,
    input wire enable, clock,
    output wire [3:0] Digit,
    output wire loadn, pgt_out
 );

    // fios auxiliares
    wire f_carry, delay;

    // conexões

    fdivider fdivider1(
        //inputs
        .clk_in(clock),
        //outputs
        .clk_out(f_carry)
    );

    encoder encoder1(
        //inputs
        .keys(keys),
        .en(enable),
        //outputs
        .loadn(loadn),
        .D(Digit)
    );

    counter counter1(
        //inputs
        .clk(clock),
        .clear(loadn),
        //outputs
        .delay(delay)
    );

    mux mux1(
        //inputs
        .cont(delay),
        .div(f_carry),
        .sel(enable),
        //outputs
        .pgt(pgt_out)
    );

endmodule

module magnetron_control (
    input wire startn, stopn, clearn, door_closed, timer_done, 
    output wire Q);

    wire s, r;

    magnetron_logic L1 (.startn(startn), 
                    .stopn(stopn),
                    .clearn(clearn),
                    .door_closed(door_closed),
                    .timer_done(timer_done),
                    .s(s), 
                    .r(r));
    
    
    latch_SR L2 (.S(s), 
                 .R(r),
                 .Q(Q)); 

endmodule

module timer(
    input wire clearn, loadn, clock, enable,
    input wire [3:0] data,
    output wire [3:0] sec_ones, sec_tens, mins,
    output wire zero
 ); 

    // fios auxiliaes
    wire zero_ones, zero_tens, zero_mins;
    wire en_sec_tens, en_mins;

    mod10 seconds_ones(
        //inputs
        .clearn(clearn),
        .loadn(loadn),
        .clock(clock),
        .en(enable),
        .data(data),
        //outputs
        .ones(sec_ones),
        .tc(en_sec_tens),
        .zero(zero_ones)
    );

    mod6 seconds_tens(
        //inputs
        .clearn(clearn),
        .loadn(loadn),
        .clock(clock),
        .en(en_sec_tens),
        .data(sec_ones),
        //outputs
        .tens(sec_tens),
        .tc(en_sec_mins),
        .zero(zero_tens)
    );

    mod10 minutes_ones(
        //inputs
        .clearn(clearn),
        .loadn(loadn),
        .clock(clock),
        .en(en_sec_mins),
        .data(sec_tens),
        //outputs
        .ones(mins),
        .zero(zero_mins)
    );

    assign zero = zero_ones && zero_tens && zero_mins;

endmodule

TIMER/counter_mod_10/mod10.v
// contador decrescente modulo 10
module mod10(
    input wire clearn, loadn, clock, en,
    input wire [3:0] data,
    output wire [3:0] ones, 
    output wire tc, zero); 
    
    // OBS:
    // data -> entrada de código BCD
    // clock -> entrada do clock 
    // loadn -> linha de controle de carga -> ativo em nível BAIXO
    // en -> entrada enable (habilitação) -> ativo em nível ALTO
    // clearn -> entrada de reset -> ativo em nível BAIXO
    // ones -> saída de código BCD
    // zero -> saída indicando que o contador chegou a zero
    // tc -> indicar quando o dígito do contador está no valor mínimo (0)
            // nesse caso TC vai para 1 e ativa o proximo contador
    

    reg [3:0] counter; // contador auxiliar para cíclos do relógio

    wire [3:0] next;
    
    always @(posedge clock, negedge clearn)
        begin
            
            // limpa o cronometro
            // caso o magnetron esteja desligado, apenas limpará o visor
            // caso esteja ligado, também encerrará a operação
            if (clearn == 1'b0)
                begin
                    counter <= 0;
                end

            else
                // se o magnetron está desligado, é possível carregar o dígito
                if (en == 1'b0)
                    begin
                        if (loadn == 1'b0)
                            begin
                                counter <= data;
                            end
                    end
                else 
                    begin
                        if (counter == 0) // magnetron ligado, iniciar contagem regressiva
                            begin
                                counter <= 9;
                            end
                        else
                            begin
                                counter <= next;
                            end
                        
                    end 
        end

    
    assign next = counter - 1;

    // quando contador chegar a zero e o cronometro estiver ativo fazer a indicação em TC
    assign tc = ((counter == 0) && (en == 1'b1)) ? 1'b1 : 1'b0;

    // quando contador chegar a zero fazer a indicação em ZERO
    assign zero = (counter == 0) ? 1'b1 : 1'b0;

    // disponibilizar o valor atual da contagem na saída
    assign ones = counter;


endmodule

TIMER/counter_mod_6/mod6.v
// contador decrescente modulo 10
module mod6(
    input wire clearn, loadn, clock, en,
    input wire [3:0] data,
    output wire [3:0] tens, 
    output wire tc, zero); 
    
    // OBS:
    // data -> entrada de código BCD
    // clock -> entrada do clock 
    // loadn -> linha de controle de carga -> ativo em nível BAIXO
    // en -> entrada enable (habilitação) -> ativo em nível ALTO
    // clearn -> entrada de reset -> ativo em nível BAIXO
    // ones -> saída de código BCD
    // zero -> saída indicando que o contador chegou a zero
    // tc -> indicar quando o dígito do contador está no valor mínimo (0)
            // nesse caso TC vai para 1 e ativa o proximo contador
    

    reg [3:0] counter; // contador auxiliar para cíclos do relógio

    wire [3:0] next;
    
    always @(posedge clock, negedge clearn)
        begin
            
            // limpa o cronometro
            // caso o magnetron esteja desligado, apenas limpará o visor
            // caso esteja ligado, também encerrará a operação
            if (clearn == 1'b0)
                begin
                    counter <= 0;
                end

            else
                // se o magnetron está desligado, é possível carregar o dígito
                if (en == 1'b0)
                    begin
                        if (loadn == 1'b0)
                            begin
                                counter <= data;
                            end
                    end
                else 
                    begin
                        if (counter == 0) // magnetron ligado, iniciar contagem regressiva
                            begin
                                counter <= 5; // note que aqui o limite superior é 5
                                // nesse caso, pode ser carregado inicialmente um número maior que 5
                                // mas, a cada cíclo de contagem sempre retornaremos ao 5 e contaremos até o 0
                            end
                        else
                            begin
                                counter <= next;
                            end
                        
                    end 
        end

    
    assign next = counter - 1;

    // quando contador chegar a zero e o cronometro estiver ativo fazer a indicação em TC
    assign tc = ((counter == 0) && (en == 1'b1)) ? 1'b1 : 1'b0;

    // quando contador chegar a zero fazer a indicação em ZERO
    assign zero = (counter == 0) ? 1'b1 : 1'b0;

    // disponibilizar o valor atual da contagem na saída
    assign tens = counter;


endmodule

BCD_encoder/mux/mux.v
module mux (
            input wire cont, div, sel,
            output reg pgt);

// OBS:
// sel -> chave de seleção que recebe sinla do enable
// cont -> entrada do mux que recebe saída do contador não reciclavel
// div -> entrada do mux que recebe saída do divisor do clock
// pgt_1Hz -> positive going trasition passada para o cronômetro

    always @(sel, div, cont) begin
        
        if (sel == 1'b1) //magnetron ligado
            pgt = div; // saida de positive going transition contínua em 1 Hz
        
        else if (sel == 1'b0)// magnetron desligado
            pgt = cont;
        
    end

    
endmodule

BCD_encoder/contador/counter.v
module counter(
    input wire clk, clear,  
    output reg delay); 
    
    // OBS:
    // clk -> entrada do clock = 100Hz
    // clear -> sinal para limpar o contdor e recomeçar a contagem
    //          indica que uma nova chave válida foi pressionada no keypad
    //          clear é ativo em nível BAIXO
    // delay -> saída de borda positiva arasada.

    reg [2:0] counter = 0; // contador auxiliar para cíclos do relógio

    always @(posedge clk, negedge clear)
        begin

            // incrementa o contador em toda borda positiva de clk
            // contador é incrementado até 7
            // contador é zerado novamente apenas quando receber entrada clear
            if (counter < 7)
                begin
                    counter <= counter + 1;  
                end

            // teste de condição de saída de borda positiva
            if (counter >= 4)
                begin
                    delay <= 1;
                    // testa condição de reset do contador
                    if (clear) // foi entrado um input válido pelo teclado
                    begin
                        counter <= 0;
                    end
                end
            else
                begin
                    delay <= 0; // pode ser que seja delay <= clk
                end 
        end

endmodule

BCD_encoder/encoder/encoder.v
module encoder (
    input wire [9:0] keys,
    input wire en,
    output reg loadn,
    output reg [3:0] D
);

    // OBS:
    // keypad -> entradas do keypad
    // en -> entrada enable
    // D -> código BCD gerado
    // loadn -> indica se a entrada é válida
    // loadn == 1 indica input inválido
    // loadn == 0 indica input válido e deve ser carregado no timer

    always @(*)
        begin
        if (en == 1'b1) // magnetron ligado

            begin
                D = 4'b0000; // nesse caso não importa o valor de de D
                loadn = 1'b1; // qualquer imput com magnetron ligado será inválido
            end

        else if (en == 1'b0) // magnetron desligado
            
            begin
                if (keys == 10'b0000000000) // nenhum digito pressionado
                    begin
                        D = 4'b0000; // nesse caso não importa o valor de de D
                        loadn = 1'b1; // não é input válido
                    end

                else if (keys == 10'b0000000001) // key 0
                    begin
                        D = 4'b0000; 
                        loadn = 1'b0;
                    end

                else if (keys == 10'b0000000010) // key 1
                    begin
                        D = 4'b0001; 
                        loadn = 1'b0;
                    end

                else if (keys == 10'b0000000100) // key 2
                    begin
                        D = 4'b0010; 
                        loadn = 1'b0;
                    end

                else if (keys == 10'b0000001000) // key 3
                    begin
                        D = 4'b0011; 
                        loadn = 1'b0;
                    end

                else if (keys == 10'b0000010000) // key 4
                    begin
                        D = 4'b0100; 
                        loadn = 1'b0;
                    end

                else if (keys == 10'b0000100000) // key 5
                    begin
                        D = 4'b0101; 
                        loadn = 1'b0;
                    end

                else if (keys == 10'b0001000000) // key 6
                    begin
                        D = 4'b0110;
                        loadn = 1'b0;
                    end

                else if (keys == 10'b0010000000) // key 7
                    begin
                        D = 4'b0111;
                        loadn = 1'b0;
                    end

                else if (keys == 10'b0100000000) // key 8
                    begin
                        D = 4'b1000;
                        loadn = 1'b0;
                    end

                else if (keys == 10'b1000000000) // key 9
                    begin
                        D = 4'b1001;
                        loadn = 1'b0;
                    end 

                else // múltiplas chaves acionadas simultaneamente
                    begin
                        D = 4'b0000; // nesse caso não importa o valor de de D
                        loadn = 1'b1; // input inválido
                    end
            end
        end

endmodule

BCD_encoder/frequency_divider/fdivider.v
module fdivider(
    input wire clk_in, // entrada do clock em 100Hz
    output clk_out); // saida do clock em 1Hz

    reg [6:0] counter = 0; // contador auxiliar para cíclos do relógio

    always @(posedge clk_in)
        begin
            // incrementa o contador em toda borda positiva de clk_in
            counter <= counter + 1;  

            // testa condição de reset do contador (100 cíclos de clock)
            if (counter >= 99)
                begin
                    counter <= 0;    
                end
        end

    // saída de clk associada ao contador de cíclos 
    assign clk_out = (counter < 50) ? 0 : 1;

endmodule

CONTROLE/latch/latch_SR.v
module latch_SR (S, R, Q);

	input S;
	input R;
	output reg Q;
    
    always @ (*) begin
		//se S e R forem iguais a 0 a saída será o Q anterior
        if (!S && !R) begin
            Q <= Q; 
        end

        else if (!S && R) begin 
            Q <= 1'b0; 
        end

        else if (S && !R) begin
            Q <= 1'b1;
        end 
    end
endmodule

CONTROLE/magnetron/magnetron_logic.v
module magnetron_logic (
    input wire startn, stopn, clearn, door_closed, timer_done, 
    output reg s, r);

    //obs: startn == 0, botão de ligar pressionado
    //stopn == 0, botão de pausar pressionado
    //clearn == 0, botão de limpar pressionado
    //door_closed == 0, porta está aberta
    //timer_done == 1, o cronômetro não está em operação

    always @ * begin
        //magnetron = 0 se a porta estiver aberta ou se stop, clear ou o timer estiverem ativos
        if (!door_closed || !stopn || !clearn || timer_done) 
            begin
                s <= 1'b0;
                r <= 1'b1;
            end
        //magnetron = 1 se start estiver ativo e a porta fechada
        else if (!startn && door_closed) 
            begin
                s <= 1'b1;
                r <= 1'b0;
            end
        else 
            begin  
                s <= 1'b0;
                r <= 1'b0;
            end
    end

endmodule

microwave_tb2.v
`timescale 1ms / 1ms
`include "microwave.v"

module microwave_tb2();
    // Inputs
    reg startn_tb, stopn_tb, clearn_tb, door_closed_tb, clock_tb;
    reg [9:0] keys_tb;

    // Outputs
    wire mag_on_tb;
    wire [6:0] ssec_ones_tb;
    wire [6:0] ssec_tens_tb;
    wire [6:0] smin_tb;
    
    // Instantiate the Unit Under Test (UUT)
    microwave DUT (.startn(startn_tb), .stopn(stopn_tb), .clearn(clearn_tb),
                    .door_closed(door_closed_tb), .clock(clock_tb), .keys(keys_tb),
                    .mag_on(mag_on_tb), .ssec_ones(ssec_ones_tb), .ssec_tens(ssec_tens_tb), .smin(smin_tb));
    
    integer i;
    
    // clock generator
    initial 
        begin
            $dumpfile("microwave_tb2.vcd");
			$dumpvars(0,microwave_tb2);

               
            // Initialize Inputs
            clock_tb = 0; 
                    
            // create input clock 100Hz
            for (i = 0; i < 30000; i = i + 1) 
                #5 clock_tb = ~clock_tb;
                

        end
    
    // test cases

    initial
        begin
            startn_tb = 0; stopn_tb = 1; clearn_tb = 1; door_closed_tb = 1;
            #1 stopn_tb = 0; 
            #1;
            // condição inicial nenhuma chave presisonada e porta fechada
            startn_tb = 1; stopn_tb = 1; clearn_tb = 1; door_closed_tb = 1;
            //insere o dígito 
            keys_tb = 10'b0000000010; // carrega 1

            #50 keys_tb = 10'b0000000000; // solta a chave
            
            #150 keys_tb = 10'b0000000001; // carrega 0

            #50 keys_tb = 10'b0000000000; // solta a chave
            
            #150 keys_tb = 10'b0000100000; // carrega 5

            #50 keys_tb = 10'b0000000000; // solta a chave

            // liga-se o magnetron

            #200 startn_tb = 0; // pressiona
            #50 startn_tb = 1; // solta

            #14950 door_closed_tb = 0;



        end
        
endmodule

microwave_tb2.vcd
$date
	Sun Dec 19 10:12:15 2021
$end
$version
	Icarus Verilog
$end
$timescale
	1ms
$end
$scope module microwave_tb2 $end
$var wire 1 ! mag_on_tb $end
$var wire 7 " smin_tb [6:0] $end
$var wire 7 # ssec_ones_tb [6:0] $end
$var wire 7 $ ssec_tens_tb [6:0] $end
$var reg 1 % clearn_tb $end
$var reg 1 & clock_tb $end
$var reg 1 ' door_closed_tb $end
$var integer 32 ( i [31:0] $end
$var reg 10 ) keys_tb [9:0] $end
$var reg 1 * startn_tb $end
$var reg 1 + stopn_tb $end
$scope module DUT $end
$var wire 1 , clearn $end
$var wire 1 - clock $end
$var wire 1 . clock_carrier $end
$var wire 4 / digit_carrier [3:0] $end
$var wire 1 0 door_closed $end
$var wire 10 1 keys [9:0] $end
$var wire 1 2 loadn_wire $end
$var wire 1 ! mag_on $end
$var wire 1 3 mag_on_wire $end
$var wire 4 4 min_wire [3:0] $end
$var wire 4 5 sec_ones_wire [3:0] $end
$var wire 4 6 sec_tens_wire [3:0] $end
$var wire 7 7 smin [6:0] $end
$var wire 7 8 ssec_ones [6:0] $end
$var wire 7 9 ssec_tens [6:0] $end
$var wire 1 : startn $end
$var wire 1 ; stopn $end
$var wire 1 < timer_done_wire $end
$scope module mag_control $end
$var wire 1 3 Q $end
$var wire 1 , clearn $end
$var wire 1 0 door_closed $end
$var wire 1 = r $end
$var wire 1 > s $end
$var wire 1 : startn $end
$var wire 1 ; stopn $end
$var wire 1 < timer_done $end
$scope module L1 $end
$var wire 1 , clearn $end
$var wire 1 0 door_closed $end
$var wire 1 : startn $end
$var wire 1 ; stopn $end
$var wire 1 < timer_done $end
$var reg 1 ? r $end
$var reg 1 @ s $end
$upscope $end
$scope module L2 $end
$var wire 1 = R $end
$var wire 1 > S $end
$var reg 1 A Q $end
$upscope $end
$upscope $end
$scope module keypad $end
$var wire 4 B Digit [3:0] $end
$var wire 1 - clock $end
$var wire 1 C delay $end
$var wire 1 3 enable $end
$var wire 1 D f_carry $end
$var wire 10 E keys [9:0] $end
$var wire 1 2 loadn $end
$var wire 1 . pgt_out $end
$scope module fdivider1 $end
$var wire 1 - clk_in $end
$var wire 1 D clk_out $end
$var reg 7 F counter [6:0] $end
$upscope $end
$scope module encoder1 $end
$var wire 1 3 en $end
$var wire 10 G keys [9:0] $end
$var reg 4 H D [3:0] $end
$var reg 1 I loadn $end
$upscope $end
$scope module counter1 $end
$var wire 1 2 clear $end
$var wire 1 - clk $end
$var reg 3 J counter [2:0] $end
$var reg 1 K delay $end
$upscope $end
$scope module mux1 $end
$var wire 1 C cont $end
$var wire 1 D div $end
$var wire 1 3 sel $end
$var reg 1 L pgt $end
$upscope $end
$upscope $end
$scope module timer1 $end
$var wire 1 , clearn $end
$var wire 1 . clock $end
$var wire 4 M data [3:0] $end
$var wire 1 N en_sec_mins $end
$var wire 1 O en_sec_tens $end
$var wire 1 3 enable $end
$var wire 1 2 loadn $end
$var wire 4 P mins [3:0] $end
$var wire 4 Q sec_ones [3:0] $end
$var wire 4 R sec_tens [3:0] $end
$var wire 1 < zero $end
$var wire 1 S zero_mins $end
$var wire 1 T zero_ones $end
$var wire 1 U zero_tens $end
$scope module seconds_ones $end
$var wire 1 , clearn $end
$var wire 1 . clock $end
$var wire 4 V data [3:0] $end
$var wire 1 3 en $end
$var wire 1 2 loadn $end
$var wire 4 W next [3:0] $end
$var wire 4 X ones [3:0] $end
$var wire 1 O tc $end
$var wire 1 T zero $end
$var reg 4 Y counter [3:0] $end
$upscope $end
$scope module seconds_tens $end
$var wire 1 , clearn $end
$var wire 1 . clock $end
$var wire 4 Z data [3:0] $end
$var wire 1 O en $end
$var wire 1 2 loadn $end
$var wire 4 [ next [3:0] $end
$var wire 1 N tc $end
$var wire 4 \ tens [3:0] $end
$var wire 1 U zero $end
$var reg 4 ] counter [3:0] $end
$upscope $end
$scope module minutes_ones $end
$var wire 1 , clearn $end
$var wire 1 . clock $end
$var wire 4 ^ data [3:0] $end
$var wire 1 N en $end
$var wire 1 2 loadn $end
$var wire 4 _ next [3:0] $end
$var wire 4 ` ones [3:0] $end
$var wire 1 a tc $end
$var wire 1 S zero $end
$var reg 4 b counter [3:0] $end
$upscope $end
$upscope $end
$scope module decoder $end
$var wire 4 c bmin [3:0] $end
$var wire 4 d bsec_ones [3:0] $end
$var wire 4 e bsec_tens [3:0] $end
$var reg 7 f smin [6:0] $end
$var reg 7 g ssec_ones [6:0] $end
$var reg 7 h ssec_tens [6:0] $end
$upscope $end
$upscope $end
$upscope $end
$enddefinitions $end
#0
$dumpvars
bx h
bx g
bx f
bx e
bx d
bx c
bx b
xa
bx `
bx _
bx ^
bx ]
bx \
bx [
bx Z
bx Y
bx X
bx W
b0 V
xU
xT
xS
bx R
bx Q
bx P
xO
xN
b0 M
0L
xK
b0 J
1I
b0 H
bx G
b0 F
bx E
0D
xC
b0 B
1A
1@
0?
1>
0=
x<
1;
0:
bx 9
bx 8
bx 7
bx 6
bx 5
bx 4
13
12
bx 1
10
b0 /
0.
0-
1,
1+
0*
bx )
b0 (
1'
0&
1%
bx $
bx #
bx "
1!
$end
#1
0a
0N
0O
xL
x.
0A
03
0!
1?
1=
0@
0>
0+
0;
#2
0L
0.
0K
0C
b1 J
0?
0=
0I
02
b1 H
b1 /
b1 B
b1 M
b1 V
b10 )
b10 1
b10 E
b10 G
1+
1;
1*
1:
#5
b10 J
b1 F
b1 (
1&
1-
#10
b10 (
0&
0-
#15
b11 J
b10 F
b11 (
1&
1-
#20
b100 (
0&
0-
#25
b100 J
b11 F
b101 (
1&
1-
#30
b110 (
0&
0-
#35
0<
b0 W
0T
b0 h
b0 $
b0 9
b110000 g
b110000 #
b110000 8
b0 f
b0 "
b0 7
b1 Y
b1 5
b1 Q
b1 X
b1 Z
b1 d
1L
1.
1K
1C
b101 J
b100 F
b111 (
1&
1-
#40
b1000 (
0&
0-
#45
b110 J
b101 F
b1001 (
1&
1-
#50
b1010 (
0&
0-
#52
1I
12
b0 H
b0 /
b0 B
b0 M
b0 V
b0 )
b0 1
b0 E
b0 G
#55
b0 J
b110 F
b1011 (
1&
1-
#60
b1100 (
0&
0-
#65
0L
0.
0K
0C
b1 J
b111 F
b1101 (
1&
1-
#70
b1110 (
0&
0-
#75
b10 J
b1000 F
b1111 (
1&
1-
#80
b10000 (
0&
0-
#85
b11 J
b1001 F
b10001 (
1&
1-
#90
b10010 (
0&
0-
#95
b100 J
b1010 F
b10011 (
1&
1-
#100
b10100 (
0&
0-
#105
1L
1.
1K
1C
b0 J
b1011 F
b10101 (
1&
1-
#110
b10110 (
0&
0-
#115
0L
0.
0K
0C
b1 J
b1100 F
b10111 (
1&
1-
#120
b11000 (
0&
0-
#125
b10 J
b1101 F
b11001 (
1&
1-
#130
b11010 (
0&
0-
#135
b11 J
b1110 F
b11011 (
1&
1-
#140
b11100 (
0&
0-
#145
b100 J
b1111 F
b11101 (
1&
1-
#150
b11110 (
0&
0-
#155
1L
1.
1K
1C
b0 J
b10000 F
b11111 (
1&
1-
#160
b100000 (
0&
0-
#165
0L
0.
0K
0C
b1 J
b10001 F
b100001 (
1&
1-
#170
b100010 (
0&
0-
#175
b10 J
b10010 F
b100011 (
1&
1-
#180
b100100 (
0&
0-
#185
b11 J
b10011 F
b100101 (
1&
1-
#190
b100110 (
0&
0-
#195
b100 J
b10100 F
b100111 (
1&
1-
#200
b101000 (
0&
0-
#202
b1111 W
1T
b0 [
0U
b110000 h
b110000 $
b110000 9
b1111110 g
b1111110 #
b1111110 8
b0 Y
b0 5
b0 Q
b0 X
b0 Z
b0 d
b1 ]
b1 6
b1 R
b1 \
b1 ^
b1 e
1L
1.
1K
1C
b101 J
0I
02
b1 )
b1 1
b1 E
b1 G
#205
b110 J
b10101 F
b101001 (
1&
1-
#210
b101010 (
0&
0-
#215
b111 J
b10110 F
b101011 (
1&
1-
#220
b101100 (
0&
0-
#225
b10111 F
b101101 (
1&
1-
#230
b101110 (
0&
0-
#235
b11000 F
b101111 (
1&
1-
#240
b110000 (
0&
0-
#245
b11001 F
b110001 (
1&
1-
#250
b110010 (
0&
0-
#252
1I
12
b0 )
b0 1
b0 E
b0 G
#255
b0 J
b11010 F
b110011 (
1&
1-
#260
b110100 (
0&
0-
#265
0L
0.
0K
0C
b1 J
b11011 F
b110101 (
1&
1-
#270
b110110 (
0&
0-
#275
b10 J
b11100 F
b110111 (
1&
1-
#280
b111000 (
0&
0-
#285
b11 J
b11101 F
b111001 (
1&
1-
#290
b111010 (
0&
0-
#295
b100 J
b11110 F
b111011 (
1&
1-
#300
b111100 (
0&
0-
#305
1L
1.
1K
1C
b0 J
b11111 F
b111101 (
1&
1-
#310
b111110 (
0&
0-
#315
0L
0.
0K
0C
b1 J
b100000 F
b111111 (
1&
1-
#320
b1000000 (
0&
0-
#325
b10 J
b100001 F
b1000001 (
1&
1-
#330
b1000010 (
0&
0-
#335
b11 J
b100010 F
b1000011 (
1&
1-
#340
b1000100 (
0&
0-
#345
b100 J
b100011 F
b1000101 (
1&
1-
#350
b1000110 (
0&
0-
#355
1L
1.
1K
1C
b0 J
b100100 F
b1000111 (
1&
1-
#360
b1001000 (
0&
0-
#365
0L
0.
0K
0C
b1 J
b100101 F
b1001001 (
1&
1-
#370
b1001010 (
0&
0-
#375
b10 J
b100110 F
b1001011 (
1&
1-
#380
b1001100 (
0&
0-
#385
b11 J
b100111 F
b1001101 (
1&
1-
#390
b1001110 (
0&
0-
#395
b100 J
b101000 F
b1001111 (
1&
1-
#400
b1010000 (
0&
0-
#402
b0 _
0S
b1111 [
1U
b100 W
0T
b1111110 h
b1111110 $
b1111110 9
b1011011 g
b1011011 #
b1011011 8
b110000 f
b110000 "
b110000 7
b1 b
b1 4
b1 P
b1 `
b1 c
b0 ]
b0 6
b0 R
b0 \
b0 ^
b0 e
b101 Y
b101 5
b101 Q
b101 X
b101 Z
b101 d
1L
1.
1K
1C
b101 J
0I
02
b101 H
b101 /
b101 B
b101 M
b101 V
b100000 )
b100000 1
b100000 E
b100000 G
#405
b110 J
b101001 F
b1010001 (
1&
1-
#410
b1010010 (
0&
0-
#415
b111 J
b101010 F
b1010011 (
1&
1-
#420
b1010100 (
0&
0-
#425
b101011 F
b1010101 (
1&
1-
#430
b1010110 (
0&
0-
#435
b101100 F
b1010111 (
1&
1-
#440
b1011000 (
0&
0-
#445
b101101 F
b1011001 (
1&
1-
#450
b1011010 (
0&
0-
#452
1I
12
b0 H
b0 /
b0 B
b0 M
b0 V
b0 )
b0 1
b0 E
b0 G
#455
b0 J
b101110 F
b1011011 (
1&
1-
#460
b1011100 (
0&
0-
#465
0L
0.
0K
0C
b1 J
b101111 F
b1011101 (
1&
1-
#470
b1011110 (
0&
0-
#475
b10 J
b110000 F
b1011111 (
1&
1-
#480
b1100000 (
0&
0-
#485
b11 J
b110001 F
b1100001 (
1&
1-
#490
b1100010 (
0&
0-
#495
1D
b100 J
b110010 F
b1100011 (
1&
1-
#500
b1100100 (
0&
0-
#505
1L
1.
1K
1C
b0 J
b110011 F
b1100101 (
1&
1-
#510
b1100110 (
0&
0-
#515
0L
0.
0K
0C
b1 J
b110100 F
b1100111 (
1&
1-
#520
b1101000 (
0&
0-
#525
b10 J
b110101 F
b1101001 (
1&
1-
#530
b1101010 (
0&
0-
#535
b11 J
b110110 F
b1101011 (
1&
1-
#540
b1101100 (
0&
0-
#545
b100 J
b110111 F
b1101101 (
1&
1-
#550
b1101110 (
0&
0-
#555
1L
1.
1K
1C
b0 J
b111000 F
b1101111 (
1&
1-
#560
b1110000 (
0&
0-
#565
0L
0.
0K
0C
b1 J
b111001 F
b1110001 (
1&
1-
#570
b1110010 (
0&
0-
#575
b10 J
b111010 F
b1110011 (
1&
1-
#580
b1110100 (
0&
0-
#585
b11 J
b111011 F
b1110101 (
1&
1-
#590
b1110110 (
0&
0-
#595
b100 J
b111100 F
b1110111 (
1&
1-
#600
b1111000 (
0&
0-
#605
1L
1.
1K
1C
b0 J
b111101 F
b1111001 (
1&
1-
#610
b1111010 (
0&
0-
#615
0L
0.
0K
0C
b1 J
b111110 F
b1111011 (
1&
1-
#620
b1111100 (
0&
0-
#625
b10 J
b111111 F
b1111101 (
1&
1-
#630
b1111110 (
0&
0-
#635
b11 J
b1000000 F
b1111111 (
1&
1-
#640
b10000000 (
0&
0-
#645
b100 J
b1000001 F
b10000001 (
1&
1-
#650
b10000010 (
0&
0-
#652
b11 W
b110011 g
b110011 #
b110011 8
b100 Y
b100 5
b100 Q
b100 X
b100 Z
b100 d
1L
1.
1A
13
1!
1@
1>
0*
0:
#655
1K
1C
b0 J
b1000010 F
b10000011 (
1&
1-
#660
b10000100 (
0&
0-
#665
0K
0C
b1 J
b1000011 F
b10000101 (
1&
1-
#670
b10000110 (
0&
0-
#675
b10 J
b1000100 F
b10000111 (
1&
1-
#680
b10001000 (
0&
0-
#685
b11 J
b1000101 F
b10001001 (
1&
1-
#690
b10001010 (
0&
0-
#695
b100 J
b1000110 F
b10001011 (
1&
1-
#700
b10001100 (
0&
0-
#702
0@
0>
1*
1:
#705
1K
1C
b0 J
b1000111 F
b10001101 (
1&
1-
#710
b10001110 (
0&
0-
#715
0K
0C
b1 J
b1001000 F
b10001111 (
1&
1-
#720
b10010000 (
0&
0-
#725
b10 J
b1001001 F
b10010001 (
1&
1-
#730
b10010010 (
0&
0-
#735
b11 J
b1001010 F
b10010011 (
1&
1-
#740
b10010100 (
0&
0-
