BCD_encoder/encoder/encoder.v
module encoder (
    input wire [9:0] keys,
    input wire en,
    output reg loadn,
    output reg [3:0] D
);

    // OBS:
    // keypad -> entradas do keypad
    // en -> entrada enable
    // D -> código BCD gerado
    // loadn -> indica se a entrada é válida
    // loadn == 1 indica input inválido
    // loadn == 0 indica input válido e deve ser carregado no timer

    always @(*)
        begin
        if (en == 1'b1) // magnetron ligado

            begin
                D = 4'b0000; // nesse caso não importa o valor de de D
                loadn = 1'b1; // qualquer imput com magnetron ligado será inválido
            end

        else if (en == 1'b0) // magnetron desligado
            
            begin
                if (keys == 10'b0000000000) // nenhum digito pressionado
                    begin
                        D = 4'b0000; // nesse caso não importa o valor de de D
                        loadn = 1'b1; // não é input válido
                    end

                else if (keys == 10'b0000000001) // key 0
                    begin
                        D = 4'b0000; 
                        loadn = 1'b0;
                    end

                else if (keys == 10'b0000000010) // key 1
                    begin
                        D = 4'b0001; 
                        loadn = 1'b0;
                    end

                else if (keys == 10'b0000000100) // key 2
                    begin
                        D = 4'b0010; 
                        loadn = 1'b0;
                    end

                else if (keys == 10'b0000001000) // key 3
                    begin
                        D = 4'b0011; 
                        loadn = 1'b0;
                    end

                else if (keys == 10'b0000010000) // key 4
                    begin
                        D = 4'b0100; 
                        loadn = 1'b0;
                    end

                else if (keys == 10'b0000100000) // key 5
                    begin
                        D = 4'b0101; 
                        loadn = 1'b0;
                    end

                else if (keys == 10'b0001000000) // key 6
                    begin
                        D = 4'b0110;
                        loadn = 1'b0;
                    end

                else if (keys == 10'b0010000000) // key 7
                    begin
                        D = 4'b0111;
                        loadn = 1'b0;
                    end

                else if (keys == 10'b0100000000) // key 8
                    begin
                        D = 4'b1000;
                        loadn = 1'b0;
                    end

                else if (keys == 10'b1000000000) // key 9
                    begin
                        D = 4'b1001;
                        loadn = 1'b0;
                    end 

                else // múltiplas chaves acionadas simultaneamente
                    begin
                        D = 4'b0000; // nesse caso não importa o valor de de D
                        loadn = 1'b1; // input inválido
                    end
            end
        end

endmodule

BCD_encoder/encoder/encoder_tb.v
`timescale 1ns/1ns
`include "encoder.v"


module encoder_tb();

	reg [9:0] keypad_tb;
    reg en_tb;
	wire [3:0] D_tb;
    wire loadn_tb;

	encoder DUT(.keys(keypad_tb), .en(en_tb), .D(D_tb), .loadn(loadn_tb));

	initial
		begin
		
			$dumpfile("encoder_tb.vcd");
			$dumpvars(0,encoder_tb);


            // casos inválidos

            // magnetron ligado
            en_tb = 1; keypad_tb = 10'b0000000000;
            #10 en_tb = 1; keypad_tb = 10'b0000001110;
            #10 en_tb = 1; keypad_tb = 10'b0001000000;
            #10 en_tb = 1; keypad_tb = 10'b0000000100;
            #10 en_tb = 1; keypad_tb = 10'b0101010101;
            #10 en_tb = 1; keypad_tb = 10'b1001000101;
            #10 en_tb = 1; keypad_tb = 10'b0111000000;

            // nenhuma chave pressionada e magnetron desligado
            #10 en_tb = 0; keypad_tb = 10'b0000000000;

            // magnetron desligado e multiplas chaves pressionadas
            #10 en_tb = 0; keypad_tb = 10'b0000000011;
            #10 en_tb = 0; keypad_tb = 10'b1000100001;
            #10 en_tb = 0; keypad_tb = 10'b0010000011;
            #10 en_tb = 0; keypad_tb = 10'b1000001111;
            #10 en_tb = 0; keypad_tb = 10'b1111111111;

            // casos válidos 
            #10 en_tb = 0; keypad_tb = 10'b0000000001; // keypad 0
            #10 en_tb = 0; keypad_tb = 10'b0000000010; // keypad 1
            #10 en_tb = 0; keypad_tb = 10'b0000000100; // keypad 2
            #10 en_tb = 0; keypad_tb = 10'b0000001000; // keypad 3
            #10 en_tb = 0; keypad_tb = 10'b0000010000; // keypad 4
            #10 en_tb = 0; keypad_tb = 10'b0000100000; // keypad 5
            #10 en_tb = 0; keypad_tb = 10'b0001000000; // keypad 6
            #10 en_tb = 0; keypad_tb = 10'b0010000000; // keypad 7
            #10 en_tb = 0; keypad_tb = 10'b0100000000; // keypad 8
            #10 en_tb = 0; keypad_tb = 10'b1000000000; // keypad 9

            #10;
		end

endmodule

BCD_encoder/encoder/encoder_tb.vcd
$date
	Wed Nov 24 09:17:16 2021
$end
$version
	Icarus Verilog
$end
$timescale
	1ns
$end
$scope module encoder_tb $end
$var wire 4 ! D_tb [3:0] $end
$var wire 1 " loadn_tb $end
$var reg 1 # en_tb $end
$var reg 10 $ keypad_tb [9:0] $end
$scope module DUT $end
$var wire 1 % en $end
$var wire 10 & keys [9:0] $end
$var reg 4 ' D [3:0] $end
$var reg 1 ( loadn $end
$upscope $end
$upscope $end
$enddefinitions $end
#0
$dumpvars
0(
b0 '
b0 &
1%
b0 $
1#
0"
b0 !
$end
#10
b1110 $
b1110 &
#20
b1000000 $
b1000000 &
#30
b100 $
b100 &
#40
b101010101 $
b101010101 &
#50
b1001000101 $
b1001000101 &
#60
b111000000 $
b111000000 &
#70
b0 $
b0 &
0#
0%
#80
b11 $
b11 &
#90
b1000100001 $
b1000100001 &
#100
b10000011 $
b10000011 &
#110
b1000001111 $
b1000001111 &
#120
b1111111111 $
b1111111111 &
#130
1(
1"
b1 $
b1 &
#140
b1 '
b1 !
b10 $
b10 &
#150
b10 '
b10 !
b100 $
b100 &
#160
b11 '
b11 !
b1000 $
b1000 &
#170
b100 '
b100 !
b10000 $
b10000 &
#180
b101 '
b101 !
b100000 $
b100000 &
#190
b110 '
b110 !
b1000000 $
b1000000 &
#200
b111 '
b111 !
b10000000 $
b10000000 &
#210
b1000 '
b1000 !
b100000000 $
b100000000 &
#220
b1001 '
b1001 !
b1000000000 $
b1000000000 &
