BCD_encoder/mux/mux.v
module mux (
            input wire cont, div, sel,
            output reg pgt);

// OBS:
// sel -> chave de seleção que recebe sinla do enable
// cont -> entrada do mux que recebe saída do contador não reciclavel
// div -> entrada do mux que recebe saída do divisor do clock
// pgt_1Hz -> positive going trasition passada para o cronômetro

    always @(sel, div, cont) begin
        
        if (sel == 1'b1) //magnetron ligado
            pgt = div; // saida de positive going transition contínua em 1 Hz
        
        else if (sel == 1'b0)// magnetron desligado
            pgt = cont;
        
    end

    
endmodule

BCD_encoder/mux/mux_tb.v
`timescale 1ns/1ns
`include "mux.v"


module mux_tb();

	reg cont_tb, div_tb, sel_tb;
	wire pgt_tb;

	mux DUT(.cont(cont_tb), .div(div_tb), .sel(sel_tb), .pgt(pgt_tb));

	initial
		begin
		
			$dumpfile("mux_tb.vcd");
			$dumpvars(0,mux_tb);
		
			cont_tb = 0; div_tb = 0; sel_tb = 0;

            #10 cont_tb = 0; div_tb = 1; sel_tb = 0;
            
            #10 cont_tb = 1; div_tb = 0; sel_tb = 0;
            #10 cont_tb = 1; div_tb = 1; sel_tb = 0;

            #10 cont_tb = 0; div_tb = 0; sel_tb = 1;
            #10 cont_tb = 0; div_tb = 1; sel_tb = 1;
            
            #10 cont_tb = 1; div_tb = 0; sel_tb = 1;
            #10 cont_tb = 1; div_tb = 1; sel_tb = 1;

            #10;
		end

endmodule

BCD_encoder/mux/mux_tb.vcd
$date
	Tue Nov 23 14:21:04 2021
$end
$version
	Icarus Verilog
$end
$timescale
	1ns
$end
$scope module mux_tb $end
$var wire 1 ! pgt_tb $end
$var reg 1 " cont_tb $end
$var reg 1 # div_tb $end
$var reg 1 $ sel_tb $end
$scope module DUT $end
$var wire 1 % cont $end
$var wire 1 & div $end
$var wire 1 ' sel $end
$var reg 1 ( pgt $end
$upscope $end
$upscope $end
$enddefinitions $end
#0
$dumpvars
0(
0'
0&
0%
0$
0#
0"
0!
$end
#10
1#
1&
#20
1(
1!
0#
0&
1"
1%
#30
1#
1&
#40
0(
0!
1$
1'
0#
0&
0"
0%
#50
1(
1!
1#
1&
#60
0(
0!
0#
0&
1"
1%
#70
1(
1!
1#
1&
