BCD_encoder/contador/counter.v
module counter(
    input wire clk, clear,  
    output reg delay); 
    
    // OBS:
    // clk -> entrada do clock = 100Hz
    // clear -> sinal para limpar o contdor e recomeçar a contagem
    //          indica que uma nova chave válida foi pressionada no keypad
    //          clear é ativo em nível BAIXO
    // delay -> saída de borda positiva arasada.

    reg [2:0] counter = 0; // contador auxiliar para cíclos do relógio

    always @(posedge clk, negedge clear)
        begin

            // incrementa o contador em toda borda positiva de clk
            // contador é incrementado até 7
            // contador é zerado novamente apenas quando receber entrada clear
            if (counter < 7)
                begin
                    counter <= counter + 1;  
                end

            // teste de condição de saída de borda positiva
            if (counter >= 4)
                begin
                    delay <= 1;
                    // testa condição de reset do contador
                    if (clear) // foi entrado um input válido pelo teclado
                    begin
                        counter <= 0;
                    end
                end
            else
                begin
                    delay <= 0; // pode ser que seja delay <= clk
                end 
        end

endmodule

BCD_encoder/contador/counter_tb.v
`timescale 1ms / 1ms
`include "counter.v"

module counter_tb();
    // Inputs
    reg clk_tb, clear_tb;
    
    // Outputs
    wire delay_tb;
    
    // Instantiate the Unit Under Test (UUT)
    // Test the clock divider in Verilog
    counter DUT (.clk(clk_tb), .delay(cdelay_tb), .clear(clear_tb));
    
    integer i;
    
    // clock generator
    initial 
        begin
            $dumpfile("counter_tb.vcd");
			$dumpvars(0,counter_tb);

               
            // Initialize Inputs
            clk_tb = 0; 
                    
            // create input clock 100Hz
            for (i = 0; i < 200; i = i + 1) 
                #5 clk_tb = ~clk_tb;
                

        end
    
    // test cases

    initial
        begin
            clear_tb = 1;

            #100 clear_tb = 0; // novo input válido

            #100 clear_tb = 1;

        end
        
endmodule

BCD_encoder/contador/counter_tb.vcd
$date
	Wed Dec 01 11:31:55 2021
$end
$version
	Icarus Verilog
$end
$timescale
	1ms
$end
$scope module counter_tb $end
$var wire 1 ! cdelay_tb $end
$var reg 1 " clear_tb $end
$var reg 1 # clk_tb $end
$var integer 32 $ i [31:0] $end
$scope module DUT $end
$var wire 1 % clear $end
$var wire 1 & clk $end
$var reg 3 ' counter [2:0] $end
$var reg 1 ( delay $end
$upscope $end
$upscope $end
$enddefinitions $end
#0
$dumpvars
x(
b0 '
0&
1%
b0 $
0#
1"
x!
$end
#5
0(
0!
b1 '
b1 $
1#
1&
#10
b10 $
0#
0&
#15
b10 '
b11 $
1#
1&
#20
b100 $
0#
0&
#25
b11 '
b101 $
1#
1&
#30
b110 $
0#
0&
#35
b100 '
b111 $
1#
1&
#40
b1000 $
0#
0&
#45
1(
1!
b0 '
b1001 $
1#
1&
#50
b1010 $
0#
0&
#55
0(
0!
b1 '
b1011 $
1#
1&
#60
b1100 $
0#
0&
#65
b10 '
b1101 $
1#
1&
#70
b1110 $
0#
0&
#75
b11 '
b1111 $
1#
1&
#80
b10000 $
0#
0&
#85
b100 '
b10001 $
1#
1&
#90
b10010 $
0#
0&
#95
1(
1!
b0 '
b10011 $
1#
1&
#100
0(
0!
b1 '
b10100 $
0#
0&
0"
0%
#105
b10 '
b10101 $
1#
1&
#110
b10110 $
0#
0&
#115
b11 '
b10111 $
1#
1&
#120
b11000 $
0#
0&
#125
b100 '
b11001 $
1#
1&
#130
b11010 $
0#
0&
#135
1(
1!
b101 '
b11011 $
1#
1&
#140
b11100 $
0#
0&
#145
b110 '
b11101 $
1#
1&
#150
b11110 $
0#
0&
#155
b111 '
b11111 $
1#
1&
#160
b100000 $
0#
0&
#165
b100001 $
1#
1&
#170
b100010 $
0#
0&
#175
b100011 $
1#
1&
#180
b100100 $
0#
0&
#185
b100101 $
1#
1&
#190
b100110 $
0#
0&
#195
b100111 $
1#
1&
#200
b101000 $
0#
0&
1"
1%
#205
b0 '
b101001 $
1#
1&
#210
b101010 $
0#
0&
#215
0(
0!
b1 '
b101011 $
1#
1&
#220
b101100 $
0#
0&
#225
b10 '
b101101 $
1#
1&
#230
b101110 $
0#
0&
#235
b11 '
b101111 $
1#
1&
#240
b110000 $
0#
0&
#245
b100 '
b110001 $
1#
1&
#250
b110010 $
0#
0&
#255
1(
1!
b0 '
b110011 $
1#
1&
#260
b110100 $
0#
0&
#265
0(
0!
b1 '
b110101 $
1#
1&
#270
b110110 $
0#
0&
#275
b10 '
b110111 $
1#
1&
#280
b111000 $
0#
0&
#285
b11 '
b111001 $
1#
1&
#290
b111010 $
0#
0&
#295
b100 '
b111011 $
1#
1&
#300
b111100 $
0#
0&
#305
1(
1!
b0 '
b111101 $
1#
1&
#310
b111110 $
0#
0&
#315
0(
0!
b1 '
b111111 $
1#
1&
#320
b1000000 $
0#
0&
#325
b10 '
b1000001 $
1#
1&
#330
b1000010 $
0#
0&
#335
b11 '
b1000011 $
1#
1&
#340
b1000100 $
0#
0&
#345
b100 '
b1000101 $
1#
1&
#350
b1000110 $
0#
0&
#355
1(
1!
b0 '
b1000111 $
1#
1&
#360
b1001000 $
0#
0&
#365
0(
0!
b1 '
b1001001 $
1#
1&
#370
b1001010 $
0#
0&
#375
b10 '
b1001011 $
1#
1&
#380
b1001100 $
0#
0&
#385
b11 '
b1001101 $
1#
1&
#390
b1001110 $
0#
0&
#395
b100 '
b1001111 $
1#
1&
#400
b1010000 $
0#
0&
#405
1(
1!
b0 '
b1010001 $
1#
1&
#410
b1010010 $
0#
0&
#415
0(
0!
b1 '
b1010011 $
1#
1&
#420
b1010100 $
0#
0&
#425
b10 '
b1010101 $
1#
1&
#430
b1010110 $
0#
0&
#435
b11 '
b1010111 $
1#
1&
#440
b1011000 $
0#
0&
#445
b100 '
b1011001 $
1#
1&
#450
b1011010 $
0#
0&
#455
1(
1!
b0 '
b1011011 $
1#
1&
#460
b1011100 $
0#
0&
#465
0(
0!
b1 '
b1011101 $
1#
1&
#470
b1011110 $
0#
0&
#475
b10 '
b1011111 $
1#
1&
#480
b1100000 $
0#
0&
#485
b11 '
b1100001 $
1#
1&
#490
b1100010 $
0#
0&
#495
b100 '
b1100011 $
1#
1&
#500
b1100100 $
0#
0&
#505
1(
1!
b0 '
b1100101 $
1#
1&
#510
b1100110 $
0#
0&
#515
0(
0!
b1 '
b1100111 $
1#
1&
#520
b1101000 $
0#
0&
#525
b10 '
b1101001 $
1#
1&
#530
b1101010 $
0#
0&
#535
b11 '
b1101011 $
1#
1&
#540
b1101100 $
0#
0&
#545
b100 '
b1101101 $
1#
1&
#550
b1101110 $
0#
0&
#555
1(
1!
b0 '
b1101111 $
1#
1&
#560
b1110000 $
0#
0&
#565
0(
0!
b1 '
b1110001 $
1#
1&
#570
b1110010 $
0#
0&
#575
b10 '
b1110011 $
1#
1&
#580
b1110100 $
0#
0&
#585
b11 '
b1110101 $
1#
1&
#590
b1110110 $
0#
0&
#595
b100 '
b1110111 $
1#
1&
#600
b1111000 $
0#
0&
#605
1(
1!
b0 '
b1111001 $
1#
1&
#610
b1111010 $
0#
0&
#615
0(
0!
b1 '
b1111011 $
1#
1&
#620
b1111100 $
0#
0&
#625
b10 '
b1111101 $
1#
1&
#630
b1111110 $
0#
0&
#635
b11 '
b1111111 $
1#
1&
#640
b10000000 $
0#
0&
#645
b100 '
b10000001 $
1#
1&
#650
b10000010 $
0#
0&
#655
1(
1!
b0 '
b10000011 $
1#
1&
#660
b10000100 $
0#
0&
#665
0(
0!
b1 '
b10000101 $
1#
1&
#670
b10000110 $
0#
0&
#675
b10 '
b10000111 $
1#
1&
#680
b10001000 $
0#
0&
#685
b11 '
b10001001 $
1#
1&
#690
b10001010 $
0#
0&
#695
b100 '
b10001011 $
1#
1&
#700
b10001100 $
0#
0&
#705
1(
1!
b0 '
b10001101 $
1#
1&
#710
b10001110 $
0#
0&
#715
0(
0!
b1 '
b10001111 $
1#
1&
#720
b10010000 $
0#
0&
#725
b10 '
b10010001 $
1#
1&
#730
b10010010 $
0#
0&
#735
b11 '
b10010011 $
1#
1&
#740
b10010100 $
0#
0&
#745
b100 '
b10010101 $
1#
1&
#750
b10010110 $
0#
0&
#755
1(
1!
b0 '
b10010111 $
1#
1&
#760
b10011000 $
0#
0&
#765
0(
0!
b1 '
b10011001 $
1#
1&
#770
b10011010 $
0#
0&
#775
b10 '
b10011011 $
1#
1&
#780
b10011100 $
0#
0&
#785
b11 '
b10011101 $
1#
1&
#790
b10011110 $
0#
0&
#795
b100 '
b10011111 $
1#
1&
#800
b10100000 $
0#
0&
#805
1(
1!
b0 '
b10100001 $
1#
1&
#810
b10100010 $
0#
0&
#815
0(
0!
b1 '
b10100011 $
1#
1&
#820
b10100100 $
0#
0&
#825
b10 '
b10100101 $
1#
1&
#830
b10100110 $
0#
0&
#835
b11 '
b10100111 $
1#
1&
#840
b10101000 $
0#
0&
#845
b100 '
b10101001 $
1#
1&
#850
b10101010 $
0#
0&
#855
1(
1!
b0 '
b10101011 $
1#
1&
#860
b10101100 $
0#
0&
#865
0(
0!
b1 '
b10101101 $
1#
1&
#870
b10101110 $
0#
0&
#875
b10 '
b10101111 $
1#
1&
#880
b10110000 $
0#
0&
#885
b11 '
b10110001 $
1#
1&
#890
b10110010 $
0#
0&
#895
b100 '
b10110011 $
1#
1&
#900
b10110100 $
0#
0&
#905
1(
1!
b0 '
b10110101 $
1#
1&
#910
b10110110 $
0#
0&
#915
0(
0!
b1 '
b10110111 $
1#
1&
#920
b10111000 $
0#
0&
#925
b10 '
b10111001 $
1#
1&
#930
b10111010 $
0#
0&
#935
b11 '
b10111011 $
1#
1&
#940
b10111100 $
0#
0&
#945
b100 '
b10111101 $
1#
1&
#950
b10111110 $
0#
0&
#955
1(
1!
b0 '
b10111111 $
1#
1&
#960
b11000000 $
0#
0&
#965
0(
0!
b1 '
b11000001 $
1#
1&
#970
b11000010 $
0#
0&
#975
b10 '
b11000011 $
1#
1&
#980
b11000100 $
0#
0&
#985
b11 '
b11000101 $
1#
1&
#990
b11000110 $
0#
0&
#995
b100 '
b11000111 $
1#
1&
#1000
b11001000 $
0#
0&
