BCD_decoder/decB2SSD.v
module decB2SSD(bsec_ones, bsec_tens, bmin, ssec_ones, ssec_tens, smin);

     //inputs/outputs 
    input [3:0] bsec_ones;
    input [3:0] bsec_tens;
    input [3:0] bmin;
    output reg [6:0] ssec_ones;
    output reg [6:0] ssec_tens;
    output reg [6:0] smin;

    // bcd to seven_segments decoder, segments are active-high

    //bloco always para converter os bcd's em SSD's
    always @(bsec_ones, bsec_tens, bmin)
    begin

        case (bmin) //case statement
            0 : smin = 7'b0000000; // apaga sempre que for 0
            1 : smin = 7'b0110000;
            2 : smin = 7'b1101101;
            3 : smin = 7'b1111001;
            4 : smin = 7'b0110011;
            5 : smin = 7'b1011011;
            6 : smin = 7'b0011111;
            7 : smin = 7'b1110000;
            8 : smin = 7'b1111111;
            9 : smin = 7'b1110011;
            //caso nao receba nenhuma dígito decimal desliga todos os segmentos.
            default : smin = 7'b0000000; 
        endcase

        case (bsec_ones) //case statement
            0 : ssec_ones = 7'b1111110;
            1 : ssec_ones = 7'b0110000;
            2 : ssec_ones = 7'b1101101;
            3 : ssec_ones = 7'b1111001;
            4 : ssec_ones = 7'b0110011;
            5 : ssec_ones = 7'b1011011;
            6 : ssec_ones = 7'b0011111;
            7 : ssec_ones = 7'b1110000;
            8 : ssec_ones = 7'b1111111;
            9 : ssec_ones = 7'b1110011;
            //caso nao receba nenhuma dígito decimal desliga todos os segmentos.
            default : ssec_ones = 7'b0000000; 
        endcase

        case (bsec_tens) //case statement
            0 : ssec_tens = 7'b1111110;
            1 : ssec_tens = 7'b0110000;
            2 : ssec_tens = 7'b1101101;
            3 : ssec_tens = 7'b1111001;
            4 : ssec_tens = 7'b0110011;
            5 : ssec_tens = 7'b1011011;
            6 : ssec_tens = 7'b0011111;
            7 : ssec_tens = 7'b1110000;
            8 : ssec_tens = 7'b1111111;
            9 : ssec_tens = 7'b1110011;
            //caso nao receba nenhuma dígito decimal desliga todos os segmentos.
            default : ssec_tens = 7'b0000000; 
        endcase

        // teste para zeros à esquerda
        if ((bmin == 0) && (bsec_tens == 0))
            begin
                ssec_tens = 7'b0000000;

                if (bsec_ones == 0)
                    begin
                        ssec_ones = 7'b0000000;
                    end
            end
    end


    //repetindo para todos os casos

endmodule

BCD_decoder/decB2SSD_tb.v
`timescale 1ns/1ns
`include "decB2SSD.v"

module decB2SSD_tb();
    
    reg [3:0] bsec_ones_tb;
    reg [3:0] bsec_tens_tb;
    reg [3:0] bmin_tb;
    wire [6:0] ssec_ones_tb;
    wire [6:0] ssec_tens_tb;
    wire [6:0] smin_tb;
    integer i;

    decB2SSD uut(
        .bsec_ones(bsec_ones_tb),
        .bsec_tens(bsec_tens_tb),
        .bmin(bmin_tb),
        .ssec_ones(ssec_ones_tb),
        .ssec_tens(ssec_tens_tb),
        .smin(smin_tb)
        );
    
    initial begin
        $dumpfile("decB2SSD_tb.vcd");
        $dumpvars(0,decB2SSD_tb);

        for(i = 0;i < 12;i = i+1) //run loop for 0 to 11.
        begin
            bsec_ones_tb = i; bsec_tens_tb = i; bmin_tb = i; 
            #10;
        end

        // testes para zeros à esquerda
        #10 bmin_tb = 2; bsec_tens_tb = 5; bsec_ones_tb = 0;
        #10 bmin_tb = 1; bsec_tens_tb = 0; bsec_ones_tb = 0;
        #10 bmin_tb = 1; bsec_tens_tb = 0; bsec_ones_tb = 6;

        //minutos aagados
        #10 bmin_tb = 0; bsec_tens_tb = 3; bsec_ones_tb = 0;

        // minuto e desenas dos segundos aagados
        #10 bmin_tb = 0; bsec_tens_tb = 0; bsec_ones_tb = 7;

        //visor completamente apagado
        #10 bmin_tb = 0; bsec_tens_tb = 0; bsec_ones_tb  = 0; 
        #10;

    end

endmodule

BCD_decoder/decB2SSD_tb.vcd
$date
	Sun Dec 19 03:55:30 2021
$end
$version
	Icarus Verilog
$end
$timescale
	1ns
$end
$scope module decB2SSD_tb $end
$var wire 7 ! smin_tb [6:0] $end
$var wire 7 " ssec_ones_tb [6:0] $end
$var wire 7 # ssec_tens_tb [6:0] $end
$var reg 4 $ bmin_tb [3:0] $end
$var reg 4 % bsec_ones_tb [3:0] $end
$var reg 4 & bsec_tens_tb [3:0] $end
$var integer 32 ' i [31:0] $end
$scope module uut $end
$var wire 4 ( bmin [3:0] $end
$var wire 4 ) bsec_ones [3:0] $end
$var wire 4 * bsec_tens [3:0] $end
$var reg 7 + smin [6:0] $end
$var reg 7 , ssec_ones [6:0] $end
$var reg 7 - ssec_tens [6:0] $end
$upscope $end
$upscope $end
$enddefinitions $end
#0
$dumpvars
b0 -
b0 ,
b0 +
b0 *
b0 )
b0 (
b0 '
b0 &
b0 %
b0 $
b0 #
b0 "
b0 !
$end
#10
b110000 -
b110000 #
b110000 ,
b110000 "
b110000 +
b110000 !
b1 $
b1 (
b1 &
b1 *
b1 %
b1 )
b1 '
#20
b1101101 -
b1101101 #
b1101101 ,
b1101101 "
b1101101 +
b1101101 !
b10 $
b10 (
b10 &
b10 *
b10 %
b10 )
b10 '
#30
b1111001 -
b1111001 #
b1111001 ,
b1111001 "
b1111001 +
b1111001 !
b11 $
b11 (
b11 &
b11 *
b11 %
b11 )
b11 '
#40
b110011 -
b110011 #
b110011 ,
b110011 "
b110011 +
b110011 !
b100 $
b100 (
b100 &
b100 *
b100 %
b100 )
b100 '
#50
b1011011 -
b1011011 #
b1011011 ,
b1011011 "
b1011011 +
b1011011 !
b101 $
b101 (
b101 &
b101 *
b101 %
b101 )
b101 '
#60
b11111 -
b11111 #
b11111 ,
b11111 "
b11111 +
b11111 !
b110 $
b110 (
b110 &
b110 *
b110 %
b110 )
b110 '
#70
b1110000 -
b1110000 #
b1110000 ,
b1110000 "
b1110000 +
b1110000 !
b111 $
b111 (
b111 &
b111 *
b111 %
b111 )
b111 '
#80
b1111111 -
b1111111 #
b1111111 ,
b1111111 "
b1111111 +
b1111111 !
b1000 $
b1000 (
b1000 &
b1000 *
b1000 %
b1000 )
b1000 '
#90
b1110011 -
b1110011 #
b1110011 ,
b1110011 "
b1110011 +
b1110011 !
b1001 $
b1001 (
b1001 &
b1001 *
b1001 %
b1001 )
b1001 '
#100
b0 -
b0 #
b0 ,
b0 "
b0 +
b0 !
b1010 $
b1010 (
b1010 &
b1010 *
b1010 %
b1010 )
b1010 '
#110
b1011 $
b1011 (
b1011 &
b1011 *
b1011 %
b1011 )
b1011 '
#120
b1100 '
#130
b1011011 -
b1011011 #
b1111110 ,
b1111110 "
b1101101 +
b1101101 !
b0 %
b0 )
b101 &
b101 *
b10 $
b10 (
#140
b1111110 -
b1111110 #
b110000 +
b110000 !
b0 &
b0 *
b1 $
b1 (
#150
b11111 ,
b11111 "
b110 %
b110 )
#160
b1111001 -
b1111001 #
b1111110 ,
b1111110 "
b0 +
b0 !
b0 %
b0 )
b11 &
b11 *
b0 $
b0 (
#170
b0 -
b0 #
b1110000 ,
b1110000 "
b111 %
b111 )
b0 &
b0 *
#180
b0 -
b0 #
b0 ,
b0 "
b0 %
b0 )
