TIMER/counter_mod_10/mod10.v
// contador decrescente modulo 10
module mod10(
    input wire clearn, loadn, clock, en,
    input wire [3:0] data,
    output wire [3:0] ones, 
    output wire tc, zero); 
    
    // OBS:
    // data -> entrada de código BCD
    // clock -> entrada do clock 
    // loadn -> linha de controle de carga -> ativo em nível BAIXO
    // en -> entrada enable (habilitação) -> ativo em nível ALTO
    // clearn -> entrada de reset -> ativo em nível BAIXO
    // ones -> saída de código BCD
    // zero -> saída indicando que o contador chegou a zero
    // tc -> indicar quando o dígito do contador está no valor mínimo (0)
            // nesse caso TC vai para 1 e ativa o proximo contador
    

    reg [3:0] counter; // contador auxiliar para cíclos do relógio

    wire [3:0] next;
    
    always @(posedge clock, negedge clearn)
        begin
            
            // limpa o cronometro
            // caso o magnetron esteja desligado, apenas limpará o visor
            // caso esteja ligado, também encerrará a operação
            if (clearn == 1'b0)
                begin
                    counter <= 0;
                end

            else
                // se o magnetron está desligado, é possível carregar o dígito
                if (en == 1'b0)
                    begin
                        if (loadn == 1'b0)
                            begin
                                counter <= data;
                            end
                    end
                else 
                    begin
                        if (counter == 0) // magnetron ligado, iniciar contagem regressiva
                            begin
                                counter <= 9;
                            end
                        else
                            begin
                                counter <= next;
                            end
                        
                    end 
        end

    
    assign next = counter - 1;

    // quando contador chegar a zero e o cronometro estiver ativo fazer a indicação em TC
    assign tc = ((counter == 0) && (en == 1'b1)) ? 1'b1 : 1'b0;

    // quando contador chegar a zero fazer a indicação em ZERO
    assign zero = (counter == 0) ? 1'b1 : 1'b0;

    // disponibilizar o valor atual da contagem na saída
    assign ones = counter;


endmodule

TIMER/counter_mod_6/mod6.v
// contador decrescente modulo 10
module mod6(
    input wire clearn, loadn, clock, en,
    input wire [3:0] data,
    output wire [3:0] tens, 
    output wire tc, zero); 
    
    // OBS:
    // data -> entrada de código BCD
    // clock -> entrada do clock 
    // loadn -> linha de controle de carga -> ativo em nível BAIXO
    // en -> entrada enable (habilitação) -> ativo em nível ALTO
    // clearn -> entrada de reset -> ativo em nível BAIXO
    // ones -> saída de código BCD
    // zero -> saída indicando que o contador chegou a zero
    // tc -> indicar quando o dígito do contador está no valor mínimo (0)
            // nesse caso TC vai para 1 e ativa o proximo contador
    

    reg [3:0] counter; // contador auxiliar para cíclos do relógio

    wire [3:0] next;
    
    always @(posedge clock, negedge clearn)
        begin
            
            // limpa o cronometro
            // caso o magnetron esteja desligado, apenas limpará o visor
            // caso esteja ligado, também encerrará a operação
            if (clearn == 1'b0)
                begin
                    counter <= 0;
                end

            else
                // se o magnetron está desligado, é possível carregar o dígito
                if (en == 1'b0)
                    begin
                        if (loadn == 1'b0)
                            begin
                                counter <= data;
                            end
                    end
                else 
                    begin
                        if (counter == 0) // magnetron ligado, iniciar contagem regressiva
                            begin
                                counter <= 5; // note que aqui o limite superior é 5
                                // nesse caso, pode ser carregado inicialmente um número maior que 5
                                // mas, a cada cíclo de contagem sempre retornaremos ao 5 e contaremos até o 0
                            end
                        else
                            begin
                                counter <= next;
                            end
                        
                    end 
        end

    
    assign next = counter - 1;

    // quando contador chegar a zero e o cronometro estiver ativo fazer a indicação em TC
    assign tc = ((counter == 0) && (en == 1'b1)) ? 1'b1 : 1'b0;

    // quando contador chegar a zero fazer a indicação em ZERO
    assign zero = (counter == 0) ? 1'b1 : 1'b0;

    // disponibilizar o valor atual da contagem na saída
    assign tens = counter;


endmodule

TIMER/timer.v

`include "counter mod 6/mod6.v"
`include "counter mod 10/mod10.v"

module timer(
    input wire clearn, loadn, clock, enable,
    input wire [3:0] data,
    output wire [3:0] sec_ones, sec_tens, mins,
    output wire zero
); 

// fios auxiliaes
wire zero_ones, zero_tens, zero_mins;
wire en_sec_tens, en_mins;

mod10 seconds_ones(
    //inputs
    .clearn(clearn),
    .loadn(loadn),
    .clock(clock),
    .en(enable),
    .data(data),
    //outputs
    .ones(sec_ones),
    .tc(en_sec_tens),
    .zero(zero_ones)
);

mod6 seconds_tens(
     //inputs
    .clearn(clearn),
    .loadn(loadn),
    .clock(clock),
    .en(en_sec_tens),
    .data(sec_ones),
    //outputs
    .tens(sec_tens),
    .tc(en_sec_mins),
    .zero(zero_tens)
);

mod10 minutes_ones(
     //inputs
    .clearn(clearn),
    .loadn(loadn),
    .clock(clock),
    .en(en_sec_mins),
    .data(sec_tens),
    //outputs
    .ones(mins),
    .zero(zero_mins)
);

assign zero = zero_ones && zero_tens && zero_mins;

endmodule

TIMER/timer_tb.v
`timescale 1ms / 1ms
`include "timer.v"

module timer_tb();
    // Inputs
    reg clock_tb, clearn_tb, loadn_tb, en_tb;
    reg [3:0] data_tb;

    // Outputs
    wire [3:0] sec_ones_tb, sec_tens_tb, mins_tb;
    wire zero_tb;
    
    // Instantiate the Unit Under Test (UUT)
    timer DUT (.clock(clock_tb), .clearn(clearn_tb), .loadn(loadn_tb), .enable(en_tb),
                .data(data_tb), .sec_ones(sec_ones_tb), .sec_tens(sec_tens_tb),
                .mins(mins_tb), .zero(zero_tb));
    
    integer i;
    
    // clock generator
    initial 
        begin
            $dumpfile("timer_tb.vcd");
			$dumpvars(0,timer_tb);

               
            // Initialize Inputs
            clock_tb = 0; 
                    
            // create input clock 1Hz
            for (i = 0; i < 200; i = i + 1) 
                #500 clock_tb = ~clock_tb;
                

        end
    
    // test cases

    initial
        begin
            
            // teste simples
            //carregamento

            clearn_tb = 1; // botão clear solto
            en_tb = 0; // magnetron desligado

            // carregar digito 
            loadn_tb = 0;
            data_tb = 7;
            #1000 loadn_tb = 1;

            #9000;

            // iniciar contagem regressiva
            en_tb = 1;

            #15000;

            // pausar contagem

            en_tb = 0;

            #5000;

            //limpar cronometro

            clearn_tb = 0;

            #5000;

            clearn_tb = 1;


            // reiniciar contagem

            en_tb = 1;

            #15000;

            // pausar cronometro
    
            en_tb = 0;

        end
        
endmodule

TIMER/timer_tb.vcd
$date
	Wed Dec 08 20:50:31 2021
$end
$version
	Icarus Verilog
$end
$timescale
	1ms
$end
$scope module timer_tb $end
$var wire 4 ! mins_tb [3:0] $end
$var wire 4 " sec_ones_tb [3:0] $end
$var wire 4 # sec_tens_tb [3:0] $end
$var wire 1 $ zero_tb $end
$var reg 1 % clearn_tb $end
$var reg 1 & clock_tb $end
$var reg 4 ' data_tb [3:0] $end
$var reg 1 ( en_tb $end
$var integer 32 ) i [31:0] $end
$var reg 1 * loadn_tb $end
$scope module DUT $end
$var wire 1 + clearn $end
$var wire 1 , clock $end
$var wire 4 - data [3:0] $end
$var wire 1 . en_sec_mins $end
$var wire 1 / en_sec_tens $end
$var wire 1 0 enable $end
$var wire 1 1 loadn $end
$var wire 4 2 mins [3:0] $end
$var wire 4 3 sec_ones [3:0] $end
$var wire 4 4 sec_tens [3:0] $end
$var wire 1 $ zero $end
$var wire 1 5 zero_mins $end
$var wire 1 6 zero_ones $end
$var wire 1 7 zero_tens $end
$scope module seconds_ones $end
$var wire 1 + clearn $end
$var wire 1 , clock $end
$var wire 4 8 data [3:0] $end
$var wire 1 0 en $end
$var wire 1 1 loadn $end
$var wire 4 9 next [3:0] $end
$var wire 4 : ones [3:0] $end
$var wire 1 / tc $end
$var wire 1 6 zero $end
$var reg 4 ; counter [3:0] $end
$upscope $end
$scope module seconds_tens $end
$var wire 1 + clearn $end
$var wire 1 , clock $end
$var wire 4 < data [3:0] $end
$var wire 1 / en $end
$var wire 1 1 loadn $end
$var wire 4 = next [3:0] $end
$var wire 1 . tc $end
$var wire 4 > tens [3:0] $end
$var wire 1 7 zero $end
$var reg 4 ? counter [3:0] $end
$upscope $end
$scope module minutes_ones $end
$var wire 1 + clearn $end
$var wire 1 , clock $end
$var wire 4 @ data [3:0] $end
$var wire 1 . en $end
$var wire 1 1 loadn $end
$var wire 4 A next [3:0] $end
$var wire 4 B ones [3:0] $end
$var wire 1 C tc $end
$var wire 1 5 zero $end
$var reg 4 D counter [3:0] $end
$upscope $end
$upscope $end
$upscope $end
$enddefinitions $end
#0
$dumpvars
bx D
0C
bx B
bx A
bx @
bx ?
bx >
bx =
bx <
bx ;
bx :
bx 9
b111 8
x7
x6
x5
bx 4
bx 3
bx 2
01
00
0/
0.
b111 -
0,
1+
0*
b0 )
0(
b111 '
0&
1%
x$
bx #
bx "
bx !
$end
#500
0$
b110 9
06
b111 ;
b111 "
b111 3
b111 :
b111 <
b1 )
1&
1,
#1000
b10 )
0&
0,
1*
11
#1500
b11 )
1&
1,
#2000
b100 )
0&
0,
#2500
b101 )
1&
1,
#3000
b110 )
0&
0,
#3500
b111 )
1&
1,
#4000
b1000 )
0&
0,
#4500
b1001 )
1&
1,
#5000
b1010 )
0&
0,
#5500
b1011 )
1&
1,
#6000
b1100 )
0&
0,
#6500
b1101 )
1&
1,
#7000
b1110 )
0&
0,
#7500
b1111 )
1&
1,
#8000
b10000 )
0&
0,
#8500
b10001 )
1&
1,
#9000
b10010 )
0&
0,
#9500
b10011 )
1&
1,
#10000
b10100 )
0&
0,
1(
10
#10500
b101 9
b110 ;
b110 "
b110 3
b110 :
b110 <
b10101 )
1&
1,
#11000
b10110 )
0&
0,
#11500
b100 9
b101 ;
b101 "
b101 3
b101 :
b101 <
b10111 )
1&
1,
#12000
b11000 )
0&
0,
#12500
b11 9
b100 ;
b100 "
b100 3
b100 :
b100 <
b11001 )
1&
1,
#13000
b11010 )
0&
0,
#13500
b10 9
b11 ;
b11 "
b11 3
b11 :
b11 <
b11011 )
1&
1,
#14000
b11100 )
0&
0,
#14500
b1 9
b10 ;
b10 "
b10 3
b10 :
b10 <
b11101 )
1&
1,
#15000
b11110 )
0&
0,
#15500
b0 9
b1 ;
b1 "
b1 3
b1 :
b1 <
b11111 )
1&
1,
#16000
b100000 )
0&
0,
#16500
xC
x.
x$
1/
b1111 9
16
b0 ;
b0 "
b0 3
b0 :
b0 <
b100001 )
1&
1,
#17000
b100010 )
0&
0,
#17500
0C
0.
0$
0/
b1001 9
06
b1010 ;
b1010 "
b1010 3
b1010 :
b1010 <
b100011 )
1&
1,
#18000
b100100 )
0&
0,
#18500
b1000 9
b1001 ;
b1001 "
b1001 3
b1001 :
b1001 <
b100101 )
1&
1,
#19000
b100110 )
0&
0,
#19500
b111 9
b1000 ;
b1000 "
b1000 3
b1000 :
b1000 <
b100111 )
1&
1,
#20000
b101000 )
0&
0,
#20500
b110 9
b111 ;
b111 "
b111 3
b111 :
b111 <
b101001 )
1&
1,
#21000
b101010 )
0&
0,
#21500
b101 9
b110 ;
b110 "
b110 3
b110 :
b110 <
b101011 )
1&
1,
#22000
b101100 )
0&
0,
#22500
b100 9
b101 ;
b101 "
b101 3
b101 :
b101 <
b101101 )
1&
1,
#23000
b101110 )
0&
0,
#23500
b11 9
b100 ;
b100 "
b100 3
b100 :
b100 <
b101111 )
1&
1,
#24000
b110000 )
0&
0,
#24500
b10 9
b11 ;
b11 "
b11 3
b11 :
b11 <
b110001 )
1&
1,
#25000
b110010 )
0&
0,
0(
00
#25500
b110011 )
1&
1,
#26000
b110100 )
0&
0,
#26500
b110101 )
1&
1,
#27000
b110110 )
0&
0,
#27500
b110111 )
1&
1,
#28000
b111000 )
0&
0,
#28500
b111001 )
1&
1,
#29000
b111010 )
0&
0,
#29500
b111011 )
1&
1,
#30000
1$
b1111 9
16
b1111 =
17
b1111 A
15
b0 ;
b0 "
b0 3
b0 :
b0 <
b0 ?
b0 #
b0 4
b0 >
b0 @
b0 D
b0 !
b0 2
b0 B
b111100 )
0&
0,
0%
0+
#30500
b111101 )
1&
1,
#31000
b111110 )
0&
0,
#31500
b111111 )
1&
1,
#32000
b1000000 )
0&
0,
#32500
b1000001 )
1&
1,
#33000
b1000010 )
0&
0,
#33500
b1000011 )
1&
1,
#34000
b1000100 )
0&
0,
#34500
b1000101 )
1&
1,
#35000
1C
1.
1/
b1000110 )
0&
0,
1(
10
1%
1+
#35500
0/
0.
0C
0$
b1001 9
06
b100 =
07
b1001 A
05
b1010 ;
b1010 "
b1010 3
b1010 :
b1010 <
b101 ?
b101 #
b101 4
b101 >
b101 @
b1010 D
b1010 !
b1010 2
b1010 B
b1000111 )
1&
1,
#36000
b1001000 )
0&
0,
#36500
b1000 9
b1001 ;
b1001 "
b1001 3
b1001 :
b1001 <
b1001001 )
1&
1,
#37000
b1001010 )
0&
0,
#37500
b111 9
b1000 ;
b1000 "
b1000 3
b1000 :
b1000 <
b1001011 )
1&
1,
#38000
b1001100 )
0&
0,
#38500
b110 9
b111 ;
b111 "
b111 3
b111 :
b111 <
b1001101 )
1&
1,
#39000
b1001110 )
0&
0,
#39500
b101 9
b110 ;
b110 "
b110 3
b110 :
b110 <
b1001111 )
1&
1,
#40000
b1010000 )
0&
0,
#40500
b100 9
b101 ;
b101 "
b101 3
b101 :
b101 <
b1010001 )
1&
1,
#41000
b1010010 )
0&
0,
#41500
b11 9
b100 ;
b100 "
b100 3
b100 :
b100 <
b1010011 )
1&
1,
#42000
b1010100 )
0&
0,
#42500
b10 9
b11 ;
b11 "
b11 3
b11 :
b11 <
b1010101 )
1&
1,
#43000
b1010110 )
0&
0,
#43500
b1 9
b10 ;
b10 "
b10 3
b10 :
b10 <
b1010111 )
1&
1,
#44000
b1011000 )
0&
0,
#44500
b0 9
b1 ;
b1 "
b1 3
b1 :
b1 <
b1011001 )
1&
1,
#45000
b1011010 )
0&
0,
#45500
1/
b1111 9
16
b0 ;
b0 "
b0 3
b0 :
b0 <
b1011011 )
1&
1,
#46000
b1011100 )
0&
0,
#46500
0/
b11 =
b1001 9
06
b100 ?
b100 #
b100 4
b100 >
b100 @
b1010 ;
b1010 "
b1010 3
b1010 :
b1010 <
b1011101 )
1&
1,
#47000
b1011110 )
0&
0,
#47500
b1000 9
b1001 ;
b1001 "
b1001 3
b1001 :
b1001 <
b1011111 )
1&
1,
#48000
b1100000 )
0&
0,
#48500
b111 9
b1000 ;
b1000 "
b1000 3
b1000 :
b1000 <
b1100001 )
1&
1,
#49000
b1100010 )
0&
0,
#49500
b110 9
b111 ;
b111 "
b111 3
b111 :
b111 <
b1100011 )
1&
1,
#50000
b1100100 )
0&
0,
0(
00
#50500
b1100101 )
1&
1,
#51000
b1100110 )
0&
0,
#51500
b1100111 )
1&
1,
#52000
b1101000 )
0&
0,
#52500
b1101001 )
1&
1,
#53000
b1101010 )
0&
0,
#53500
b1101011 )
1&
1,
#54000
b1101100 )
0&
0,
#54500
b1101101 )
1&
1,
#55000
b1101110 )
0&
0,
#55500
b1101111 )
1&
1,
#56000
b1110000 )
0&
0,
#56500
b1110001 )
1&
1,
#57000
b1110010 )
0&
0,
#57500
b1110011 )
1&
1,
#58000
b1110100 )
0&
0,
#58500
b1110101 )
1&
1,
#59000
b1110110 )
0&
0,
#59500
b1110111 )
1&
1,
#60000
b1111000 )
0&
0,
#60500
b1111001 )
1&
1,
#61000
b1111010 )
0&
0,
#61500
b1111011 )
1&
1,
#62000
b1111100 )
0&
0,
#62500
b1111101 )
1&
1,
#63000
b1111110 )
0&
0,
#63500
b1111111 )
1&
1,
#64000
b10000000 )
0&
0,
#64500
b10000001 )
1&
1,
#65000
b10000010 )
0&
0,
#65500
b10000011 )
1&
1,
#66000
b10000100 )
0&
0,
#66500
b10000101 )
1&
1,
#67000
b10000110 )
0&
0,
#67500
b10000111 )
1&
1,
#68000
b10001000 )
0&
0,
#68500
b10001001 )
1&
1,
#69000
b10001010 )
0&
0,
#69500
b10001011 )
1&
1,
#70000
b10001100 )
0&
0,
#70500
b10001101 )
1&
1,
#71000
b10001110 )
0&
0,
#71500
b10001111 )
1&
1,
#72000
b10010000 )
0&
0,
#72500
b10010001 )
1&
1,
#73000
b10010010 )
0&
0,
#73500
b10010011 )
1&
1,
#74000
b10010100 )
0&
0,
#74500
b10010101 )
1&
1,
#75000
b10010110 )
0&
0,
#75500
b10010111 )
1&
1,
#76000
b10011000 )
0&
0,
#76500
b10011001 )
1&
1,
#77000
b10011010 )
0&
0,
#77500
b10011011 )
1&
1,
#78000
b10011100 )
0&
0,
#78500
b10011101 )
1&
1,
#79000
b10011110 )
0&
0,
#79500
b10011111 )
1&
1,
#80000
b10100000 )
0&
0,
#80500
b10100001 )
1&
1,
#81000
b10100010 )
0&
0,
#81500
b10100011 )
1&
1,
#82000
b10100100 )
0&
0,
#82500
b10100101 )
1&
1,
#83000
b10100110 )
0&
0,
#83500
b10100111 )
1&
1,
#84000
b10101000 )
0&
0,
#84500
b10101001 )
1&
1,
#85000
b10101010 )
0&
0,
#85500
b10101011 )
1&
1,
#86000
b10101100 )
0&
0,
#86500
b10101101 )
1&
1,
#87000
b10101110 )
0&
0,
#87500
b10101111 )
1&
1,
#88000
b10110000 )
0&
0,
#88500
b10110001 )
1&
1,
#89000
b10110010 )
0&
0,
#89500
b10110011 )
1&
1,
#90000
b10110100 )
0&
0,
#90500
b10110101 )
1&
1,
#91000
b10110110 )
0&
0,
#91500
b10110111 )
1&
1,
#92000
b10111000 )
0&
0,
#92500
b10111001 )
1&
1,
#93000
b10111010 )
0&
0,
#93500
b10111011 )
1&
1,
#94000
b10111100 )
0&
0,
#94500
b10111101 )
1&
1,
#95000
b10111110 )
0&
0,
#95500
b10111111 )
1&
1,
#96000
b11000000 )
0&
0,
#96500
b11000001 )
1&
1,
#97000
b11000010 )
0&
0,
#97500
b11000011 )
1&
1,
#98000
b11000100 )
0&
0,
#98500
b11000101 )
1&
1,
#99000
b11000110 )
0&
0,
#99500
b11000111 )
1&
1,
#100000
b11001000 )
0&
0,
