CONTROLE/latch/latch_SR.v
module latch_SR (S, R, Q);

	input S;
	input R;
	output reg Q;
    
    always @ (*) begin
		//se S e R forem iguais a 0 a saída será o Q anterior
        if (!S && !R) begin
            Q <= Q; 
        end

        else if (!S && R) begin 
            Q <= 1'b0; 
        end

        else if (S && !R) begin
            Q <= 1'b1;
        end 
    end
endmodule

CONTROLE/latch/latch_SR_tb.v
`timescale 1ns/1ps
`include "latch_SR.v"

module latch_SR_TB();

	//inputs
	reg S_TB, R_TB;

	//outputs
	wire Q_TB;

	latch_SR DUT(.S(S_TB), .R(R_TB), .Q(Q_TB));

	initial
		begin
		
			$dumpfile("latch_SR_TB.vcd");
			$dumpvars(0,latch_SR_TB);
		
			S_TB = 1'b1; R_TB = 1'b0;
        #10 S_TB = 1'b0; R_TB = 1'b0;
		#10 S_TB = 1'b1; R_TB = 1'b1;
		#10 S_TB = 1'b0; R_TB = 1'b0;
		#10 S_TB = 1'b0; R_TB = 1'b1;
		#10 S_TB = 1'b0; R_TB = 1'b0;
        #10	S_TB = 1'b1; R_TB = 1'b0;
        #10 S_TB = 1'b0; R_TB = 1'b0;        
        #10;

		end

endmodule

CONTROLE/latch/latch_SR_TB.vcd
$date
	Sun Dec 19 04:20:54 2021
$end
$version
	Icarus Verilog
$end
$timescale
	1ps
$end
$scope module latch_SR_TB $end
$var wire 1 ! Q_TB $end
$var reg 1 " R_TB $end
$var reg 1 # S_TB $end
$scope module DUT $end
$var wire 1 $ R $end
$var wire 1 % S $end
$var reg 1 & Q $end
$upscope $end
$upscope $end
$enddefinitions $end
#0
$dumpvars
1&
1%
0$
1#
0"
1!
$end
#10000
0#
0%
#20000
1"
1$
1#
1%
#30000
0"
0$
0#
0%
#40000
0&
0!
1"
1$
#50000
0"
0$
#60000
1&
1!
1#
1%
#70000
0#
0%
