BCD_encoder/frequency_divider/fdivider.v
module fdivider(
    input wire clk_in, // entrada do clock em 100Hz
    output clk_out); // saida do clock em 1Hz

    reg [6:0] counter = 0; // contador auxiliar para cíclos do relógio

    always @(posedge clk_in)
        begin
            // incrementa o contador em toda borda positiva de clk_in
            counter <= counter + 1;  

            // testa condição de reset do contador (100 cíclos de clock)
            if (counter >= 99)
                begin
                    counter <= 0;    
                end
        end

    // saída de clk associada ao contador de cíclos 
    assign clk_out = (counter < 50) ? 0 : 1;

endmodule

BCD_encoder/frequency_divider/fdivider_tb.v
`timescale 1ms / 1ms
`include "fdivider.v"

module fdivider_tb();
    // Inputs
    reg clk_in_tb;
    
    // Outputs
    wire clk_out_tb;
    
    // Instantiate the Unit Under Test (UUT)
    // Test the clock divider in Verilog
    fdivider DUT (.clk_in(clk_in_tb), .clk_out(clk_out_tb));
    
    integer i;

    initial 
        begin
            $dumpfile("fdivider_tb.vcd");
			$dumpvars(0,fdivider_tb);
           
            // Initialize Inputs
            clk_in_tb = 0;
            
            // create input clock 100Hz
            for (i = 0; i < 1001; i = i + 1) 
                #5 clk_in_tb = ~clk_in_tb;

        end
        
endmodule

BCD_encoder/frequency_divider/fdivider_tb.vcd
$date
	Wed Dec 01 07:46:41 2021
$end
$version
	Icarus Verilog
$end
$timescale
	1ms
$end
$scope module fdivider_tb $end
$var wire 1 ! clk_out_tb $end
$var reg 1 " clk_in_tb $end
$var integer 32 # i [31:0] $end
$scope module DUT $end
$var wire 1 $ clk_in $end
$var wire 1 ! clk_out $end
$var reg 7 % counter [6:0] $end
$upscope $end
$upscope $end
$enddefinitions $end
#0
$dumpvars
b0 %
0$
b0 #
0"
0!
$end
#5
b1 %
b1 #
1"
1$
#10
b10 #
0"
0$
#15
b10 %
b11 #
1"
1$
#20
b100 #
0"
0$
#25
b11 %
b101 #
1"
1$
#30
b110 #
0"
0$
#35
b100 %
b111 #
1"
1$
#40
b1000 #
0"
0$
#45
b101 %
b1001 #
1"
1$
#50
b1010 #
0"
0$
#55
b110 %
b1011 #
1"
1$
#60
b1100 #
0"
0$
#65
b111 %
b1101 #
1"
1$
#70
b1110 #
0"
0$
#75
b1000 %
b1111 #
1"
1$
#80
b10000 #
0"
0$
#85
b1001 %
b10001 #
1"
1$
#90
b10010 #
0"
0$
#95
b1010 %
b10011 #
1"
1$
#100
b10100 #
0"
0$
#105
b1011 %
b10101 #
1"
1$
#110
b10110 #
0"
0$
#115
b1100 %
b10111 #
1"
1$
#120
b11000 #
0"
0$
#125
b1101 %
b11001 #
1"
1$
#130
b11010 #
0"
0$
#135
b1110 %
b11011 #
1"
1$
#140
b11100 #
0"
0$
#145
b1111 %
b11101 #
1"
1$
#150
b11110 #
0"
0$
#155
b10000 %
b11111 #
1"
1$
#160
b100000 #
0"
0$
#165
b10001 %
b100001 #
1"
1$
#170
b100010 #
0"
0$
#175
b10010 %
b100011 #
1"
1$
#180
b100100 #
0"
0$
#185
b10011 %
b100101 #
1"
1$
#190
b100110 #
0"
0$
#195
b10100 %
b100111 #
1"
1$
#200
b101000 #
0"
0$
#205
b10101 %
b101001 #
1"
1$
#210
b101010 #
0"
0$
#215
b10110 %
b101011 #
1"
1$
#220
b101100 #
0"
0$
#225
b10111 %
b101101 #
1"
1$
#230
b101110 #
0"
0$
#235
b11000 %
b101111 #
1"
1$
#240
b110000 #
0"
0$
#245
b11001 %
b110001 #
1"
1$
#250
b110010 #
0"
0$
#255
b11010 %
b110011 #
1"
1$
#260
b110100 #
0"
0$
#265
b11011 %
b110101 #
1"
1$
#270
b110110 #
0"
0$
#275
b11100 %
b110111 #
1"
1$
#280
b111000 #
0"
0$
#285
b11101 %
b111001 #
1"
1$
#290
b111010 #
0"
0$
#295
b11110 %
b111011 #
1"
1$
#300
b111100 #
0"
0$
#305
b11111 %
b111101 #
1"
1$
#310
b111110 #
0"
0$
#315
b100000 %
b111111 #
1"
1$
#320
b1000000 #
0"
0$
#325
b100001 %
b1000001 #
1"
1$
#330
b1000010 #
0"
0$
#335
b100010 %
b1000011 #
1"
1$
#340
b1000100 #
0"
0$
#345
b100011 %
b1000101 #
1"
1$
#350
b1000110 #
0"
0$
#355
b100100 %
b1000111 #
1"
1$
#360
b1001000 #
0"
0$
#365
b100101 %
b1001001 #
1"
1$
#370
b1001010 #
0"
0$
#375
b100110 %
b1001011 #
1"
1$
#380
b1001100 #
0"
0$
#385
b100111 %
b1001101 #
1"
1$
#390
b1001110 #
0"
0$
#395
b101000 %
b1001111 #
1"
1$
#400
b1010000 #
0"
0$
#405
b101001 %
b1010001 #
1"
1$
#410
b1010010 #
0"
0$
#415
b101010 %
b1010011 #
1"
1$
#420
b1010100 #
0"
0$
#425
b101011 %
b1010101 #
1"
1$
#430
b1010110 #
0"
0$
#435
b101100 %
b1010111 #
1"
1$
#440
b1011000 #
0"
0$
#445
b101101 %
b1011001 #
1"
1$
#450
b1011010 #
0"
0$
#455
b101110 %
b1011011 #
1"
1$
#460
b1011100 #
0"
0$
#465
b101111 %
b1011101 #
1"
1$
#470
b1011110 #
0"
0$
#475
b110000 %
b1011111 #
1"
1$
#480
b1100000 #
0"
0$
#485
b110001 %
b1100001 #
1"
1$
#490
b1100010 #
0"
0$
#495
1!
b110010 %
b1100011 #
1"
1$
#500
b1100100 #
0"
0$
#505
b110011 %
b1100101 #
1"
1$
#510
b1100110 #
0"
0$
#515
b110100 %
b1100111 #
1"
1$
#520
b1101000 #
0"
0$
#525
b110101 %
b1101001 #
1"
1$
#530
b1101010 #
0"
0$
#535
b110110 %
b1101011 #
1"
1$
#540
b1101100 #
0"
0$
#545
b110111 %
b1101101 #
1"
1$
#550
b1101110 #
0"
0$
#555
b111000 %
b1101111 #
1"
1$
#560
b1110000 #
0"
0$
#565
b111001 %
b1110001 #
1"
1$
#570
b1110010 #
0"
0$
#575
b111010 %
b1110011 #
1"
1$
#580
b1110100 #
0"
0$
#585
b111011 %
b1110101 #
1"
1$
#590
b1110110 #
0"
0$
#595
b111100 %
b1110111 #
1"
1$
#600
b1111000 #
0"
0$
#605
b111101 %
b1111001 #
1"
1$
#610
b1111010 #
0"
0$
#615
b111110 %
b1111011 #
1"
1$
#620
b1111100 #
0"
0$
#625
b111111 %
b1111101 #
1"
1$
#630
b1111110 #
0"
0$
#635
b1000000 %
b1111111 #
1"
1$
#640
b10000000 #
0"
0$
#645
b1000001 %
b10000001 #
1"
1$
#650
b10000010 #
0"
0$
#655
b1000010 %
b10000011 #
1"
1$
#660
b10000100 #
0"
0$
#665
b1000011 %
b10000101 #
1"
1$
#670
b10000110 #
0"
0$
#675
b1000100 %
b10000111 #
1"
1$
#680
b10001000 #
0"
0$
#685
b1000101 %
b10001001 #
1"
1$
#690
b10001010 #
0"
0$
#695
b1000110 %
b10001011 #
1"
1$
#700
b10001100 #
0"
0$
#705
b1000111 %
b10001101 #
1"
1$
#710
b10001110 #
0"
0$
#715
b1001000 %
b10001111 #
1"
1$
#720
b10010000 #
0"
0$
#725
b1001001 %
b10010001 #
1"
1$
#730
b10010010 #
0"
0$
#735
b1001010 %
b10010011 #
1"
1$
#740
b10010100 #
0"
0$
#745
b1001011 %
b10010101 #
1"
1$
#750
b10010110 #
0"
0$
#755
b1001100 %
b10010111 #
1"
1$
#760
b10011000 #
0"
0$
#765
b1001101 %
b10011001 #
1"
1$
#770
b10011010 #
0"
0$
#775
b1001110 %
b10011011 #
1"
1$
#780
b10011100 #
0"
0$
#785
b1001111 %
b10011101 #
1"
1$
#790
b10011110 #
0"
0$
#795
b1010000 %
b10011111 #
1"
1$
#800
b10100000 #
0"
0$
#805
b1010001 %
b10100001 #
1"
1$
#810
b10100010 #
0"
0$
#815
b1010010 %
b10100011 #
1"
1$
#820
b10100100 #
0"
0$
#825
b1010011 %
b10100101 #
1"
1$
#830
b10100110 #
0"
0$
#835
b1010100 %
b10100111 #
1"
1$
#840
b10101000 #
0"
0$
#845
b1010101 %
b10101001 #
1"
1$
#850
b10101010 #
0"
0$
#855
b1010110 %
b10101011 #
1"
1$
#860
b10101100 #
0"
0$
#865
b1010111 %
b10101101 #
1"
1$
#870
b10101110 #
0"
0$
#875
b1011000 %
b10101111 #
1"
1$
#880
b10110000 #
0"
0$
#885
b1011001 %
b10110001 #
1"
1$
#890
b10110010 #
0"
0$
#895
b1011010 %
b10110011 #
1"
1$
#900
b10110100 #
0"
0$
#905
b1011011 %
b10110101 #
1"
1$
#910
b10110110 #
0"
0$
#915
b1011100 %
b10110111 #
1"
1$
#920
b10111000 #
0"
0$
#925
b1011101 %
b10111001 #
1"
1$
#930
b10111010 #
0"
0$
#935
b1011110 %
b10111011 #
1"
1$
#940
b10111100 #
0"
0$
#945
b1011111 %
b10111101 #
1"
1$
#950
b10111110 #
0"
0$
#955
b1100000 %
b10111111 #
1"
1$
#960
b11000000 #
0"
0$
#965
b1100001 %
b11000001 #
1"
1$
#970
b11000010 #
0"
0$
#975
b1100010 %
b11000011 #
1"
1$
#980
b11000100 #
0"
0$
#985
b1100011 %
b11000101 #
1"
1$
#990
b11000110 #
0"
0$
#995
0!
b0 %
b11000111 #
1"
1$
#1000
b11001000 #
0"
0$
#1005
b1 %
b11001001 #
1"
1$
#1010
b11001010 #
0"
0$
#1015
b10 %
b11001011 #
1"
1$
#1020
b11001100 #
0"
0$
#1025
b11 %
b11001101 #
1"
1$
#1030
b11001110 #
0"
0$
#1035
b100 %
b11001111 #
1"
1$
#1040
b11010000 #
0"
0$
#1045
b101 %
b11010001 #
1"
1$
#1050
b11010010 #
0"
0$
#1055
b110 %
b11010011 #
1"
1$
#1060
b11010100 #
0"
0$
#1065
b111 %
b11010101 #
1"
1$
#1070
b11010110 #
0"
0$
#1075
b1000 %
b11010111 #
1"
1$
#1080
b11011000 #
0"
0$
#1085
b1001 %
b11011001 #
1"
1$
#1090
b11011010 #
0"
0$
#1095
b1010 %
b11011011 #
1"
1$
#1100
b11011100 #
0"
0$
#1105
b1011 %
b11011101 #
1"
1$
#1110
b11011110 #
0"
0$
#1115
b1100 %
b11011111 #
1"
1$
#1120
b11100000 #
0"
0$
#1125
b1101 %
b11100001 #
1"
1$
#1130
b11100010 #
0"
0$
#1135
b1110 %
b11100011 #
1"
1$
#1140
b11100100 #
0"
0$
#1145
b1111 %
b11100101 #
1"
1$
#1150
b11100110 #
0"
0$
#1155
b10000 %
b11100111 #
1"
1$
#1160
b11101000 #
0"
0$
#1165
b10001 %
b11101001 #
1"
1$
#1170
b11101010 #
0"
0$
#1175
b10010 %
b11101011 #
1"
1$
#1180
b11101100 #
0"
0$
#1185
b10011 %
b11101101 #
1"
1$
#1190
b11101110 #
0"
0$
#1195
b10100 %
b11101111 #
1"
1$
#1200
b11110000 #
0"
0$
#1205
b10101 %
b11110001 #
1"
1$
#1210
b11110010 #
0"
0$
#1215
b10110 %
b11110011 #
1"
1$
#1220
b11110100 #
0"
0$
#1225
b10111 %
b11110101 #
1"
1$
#1230
b11110110 #
0"
0$
#1235
b11000 %
b11110111 #
1"
1$
#1240
b11111000 #
0"
0$
#1245
b11001 %
b11111001 #
1"
1$
#1250
b11111010 #
0"
0$
#1255
b11010 %
b11111011 #
1"
1$
#1260
b11111100 #
0"
0$
#1265
b11011 %
b11111101 #
1"
1$
#1270
b11111110 #
0"
0$
#1275
b11100 %
b11111111 #
1"
1$
#1280
b100000000 #
0"
0$
#1285
b11101 %
b100000001 #
1"
1$
#1290
b100000010 #
0"
0$
#1295
b11110 %
b100000011 #
1"
1$
#1300
b100000100 #
0"
0$
#1305
b11111 %
b100000101 #
1"
1$
#1310
b100000110 #
0"
0$
#1315
b100000 %
b100000111 #
1"
1$
#1320
b100001000 #
0"
0$
#1325
b100001 %
b100001001 #
1"
1$
#1330
b100001010 #
0"
0$
#1335
b100010 %
b100001011 #
1"
1$
#1340
b100001100 #
0"
0$
#1345
b100011 %
b100001101 #
1"
1$
#1350
b100001110 #
0"
0$
#1355
b100100 %
b100001111 #
1"
1$
#1360
b100010000 #
0"
0$
#1365
b100101 %
b100010001 #
1"
1$
#1370
b100010010 #
0"
0$
#1375
b100110 %
b100010011 #
1"
1$
#1380
b100010100 #
0"
0$
#1385
b100111 %
b100010101 #
1"
1$
#1390
b100010110 #
0"
0$
#1395
b101000 %
b100010111 #
1"
1$
#1400
b100011000 #
0"
0$
#1405
b101001 %
b100011001 #
1"
1$
#1410
b100011010 #
0"
0$
#1415
b101010 %
b100011011 #
1"
1$
#1420
b100011100 #
0"
0$
#1425
b101011 %
b100011101 #
1"
1$
#1430
b100011110 #
0"
0$
#1435
b101100 %
b100011111 #
1"
1$
#1440
b100100000 #
0"
0$
#1445
b101101 %
b100100001 #
1"
1$
#1450
b100100010 #
0"
0$
#1455
b101110 %
b100100011 #
1"
1$
#1460
b100100100 #
0"
0$
#1465
b101111 %
b100100101 #
1"
1$
#1470
b100100110 #
0"
0$
#1475
b110000 %
b100100111 #
1"
1$
#1480
b100101000 #
0"
0$
#1485
b110001 %
b100101001 #
1"
1$
#1490
b100101010 #
0"
0$
#1495
1!
b110010 %
b100101011 #
1"
1$
#1500
b100101100 #
0"
0$
#1505
b110011 %
b100101101 #
1"
1$
#1510
b100101110 #
0"
0$
#1515
b110100 %
b100101111 #
1"
1$
#1520
b100110000 #
0"
0$
#1525
b110101 %
b100110001 #
1"
1$
#1530
b100110010 #
0"
0$
#1535
b110110 %
b100110011 #
1"
1$
#1540
b100110100 #
0"
0$
#1545
b110111 %
b100110101 #
1"
1$
#1550
b100110110 #
0"
0$
#1555
b111000 %
b100110111 #
1"
1$
#1560
b100111000 #
0"
0$
#1565
b111001 %
b100111001 #
1"
1$
#1570
b100111010 #
0"
0$
#1575
b111010 %
b100111011 #
1"
1$
#1580
b100111100 #
0"
0$
#1585
b111011 %
b100111101 #
1"
1$
#1590
b100111110 #
0"
0$
#1595
b111100 %
b100111111 #
1"
1$
#1600
b101000000 #
0"
0$
#1605
b111101 %
b101000001 #
1"
1$
#1610
b101000010 #
0"
0$
#1615
b111110 %
b101000011 #
1"
1$
#1620
b101000100 #
0"
0$
#1625
b111111 %
b101000101 #
1"
1$
#1630
b101000110 #
0"
0$
#1635
b1000000 %
b101000111 #
1"
1$
#1640
b101001000 #
0"
0$
#1645
b1000001 %
b101001001 #
1"
1$
#1650
b101001010 #
0"
0$
#1655
b1000010 %
b101001011 #
1"
1$
#1660
b101001100 #
0"
0$
#1665
b1000011 %
b101001101 #
1"
1$
#1670
b101001110 #
0"
0$
#1675
b1000100 %
b101001111 #
1"
1$
#1680
b101010000 #
0"
0$
#1685
b1000101 %
b101010001 #
1"
1$
#1690
b101010010 #
0"
0$
#1695
b1000110 %
b101010011 #
1"
1$
#1700
b101010100 #
0"
0$
#1705
b1000111 %
b101010101 #
1"
1$
#1710
b101010110 #
0"
0$
#1715
b1001000 %
b101010111 #
1"
1$
#1720
b101011000 #
0"
0$
#1725
b1001001 %
b101011001 #
1"
1$
#1730
b101011010 #
0"
0$
#1735
b1001010 %
b101011011 #
1"
1$
#1740
b101011100 #
0"
0$
#1745
b1001011 %
b101011101 #
1"
1$
#1750
b101011110 #
0"
0$
#1755
b1001100 %
b101011111 #
1"
1$
#1760
b101100000 #
0"
0$
#1765
b1001101 %
b101100001 #
1"
1$
#1770
b101100010 #
0"
0$
#1775
b1001110 %
b101100011 #
1"
1$
#1780
b101100100 #
0"
0$
#1785
b1001111 %
b101100101 #
1"
1$
#1790
b101100110 #
0"
0$
#1795
b1010000 %
b101100111 #
1"
1$
#1800
b101101000 #
0"
0$
#1805
b1010001 %
b101101001 #
1"
1$
#1810
b101101010 #
0"
0$
#1815
b1010010 %
b101101011 #
1"
1$
#1820
b101101100 #
0"
0$
#1825
b1010011 %
b101101101 #
1"
1$
#1830
b101101110 #
0"
0$
#1835
b1010100 %
b101101111 #
1"
1$
#1840
b101110000 #
0"
0$
#1845
b1010101 %
b101110001 #
1"
1$
#1850
b101110010 #
0"
0$
#1855
b1010110 %
b101110011 #
1"
1$
#1860
b101110100 #
0"
0$
#1865
b1010111 %
b101110101 #
1"
1$
#1870
b101110110 #
0"
0$
#1875
b1011000 %
b101110111 #
1"
1$
#1880
b101111000 #
0"
0$
#1885
b1011001 %
b101111001 #
1"
1$
#1890
b101111010 #
0"
0$
#1895
b1011010 %
b101111011 #
1"
1$
#1900
b101111100 #
0"
0$
#1905
b1011011 %
b101111101 #
1"
1$
#1910
b101111110 #
0"
0$
#1915
b1011100 %
b101111111 #
1"
1$
#1920
b110000000 #
0"
0$
#1925
b1011101 %
b110000001 #
1"
1$
#1930
b110000010 #
0"
0$
#1935
b1011110 %
b110000011 #
1"
1$
#1940
b110000100 #
0"
0$
#1945
b1011111 %
b110000101 #
1"
1$
#1950
b110000110 #
0"
0$
#1955
b1100000 %
b110000111 #
1"
1$
#1960
b110001000 #
0"
0$
#1965
b1100001 %
b110001001 #
1"
1$
#1970
b110001010 #
0"
0$
#1975
b1100010 %
b110001011 #
1"
1$
#1980
b110001100 #
0"
0$
#1985
b1100011 %
b110001101 #
1"
1$
#1990
b110001110 #
0"
0$
#1995
0!
b0 %
b110001111 #
1"
1$
#2000
b110010000 #
0"
0$
#2005
b1 %
b110010001 #
1"
1$
#2010
b110010010 #
0"
0$
#2015
b10 %
b110010011 #
1"
1$
#2020
b110010100 #
0"
0$
#2025
b11 %
b110010101 #
1"
1$
#2030
b110010110 #
0"
0$
#2035
b100 %
b110010111 #
1"
1$
#2040
b110011000 #
0"
0$
#2045
b101 %
b110011001 #
1"
1$
#2050
b110011010 #
0"
0$
#2055
b110 %
b110011011 #
1"
1$
#2060
b110011100 #
0"
0$
#2065
b111 %
b110011101 #
1"
1$
#2070
b110011110 #
0"
0$
#2075
b1000 %
b110011111 #
1"
1$
#2080
b110100000 #
0"
0$
#2085
b1001 %
b110100001 #
1"
1$
#2090
b110100010 #
0"
0$
#2095
b1010 %
b110100011 #
1"
1$
#2100
b110100100 #
0"
0$
#2105
b1011 %
b110100101 #
1"
1$
#2110
b110100110 #
0"
0$
#2115
b1100 %
b110100111 #
1"
1$
#2120
b110101000 #
0"
0$
#2125
b1101 %
b110101001 #
1"
1$
#2130
b110101010 #
0"
0$
#2135
b1110 %
b110101011 #
1"
1$
#2140
b110101100 #
0"
0$
#2145
b1111 %
b110101101 #
1"
1$
#2150
b110101110 #
0"
0$
#2155
b10000 %
b110101111 #
1"
1$
#2160
b110110000 #
0"
0$
#2165
b10001 %
b110110001 #
1"
1$
#2170
b110110010 #
0"
0$
#2175
b10010 %
b110110011 #
1"
1$
#2180
b110110100 #
0"
0$
#2185
b10011 %
b110110101 #
1"
1$
#2190
b110110110 #
0"
0$
#2195
b10100 %
b110110111 #
1"
1$
#2200
b110111000 #
0"
0$
#2205
b10101 %
b110111001 #
1"
1$
#2210
b110111010 #
0"
0$
#2215
b10110 %
b110111011 #
1"
1$
#2220
b110111100 #
0"
0$
#2225
b10111 %
b110111101 #
1"
1$
#2230
b110111110 #
0"
0$
#2235
b11000 %
b110111111 #
1"
1$
#2240
b111000000 #
0"
0$
#2245
b11001 %
b111000001 #
1"
1$
#2250
b111000010 #
0"
0$
#2255
b11010 %
b111000011 #
1"
1$
#2260
b111000100 #
0"
0$
#2265
b11011 %
b111000101 #
1"
1$
#2270
b111000110 #
0"
0$
#2275
b11100 %
b111000111 #
1"
1$
#2280
b111001000 #
0"
0$
#2285
b11101 %
b111001001 #
1"
1$
#2290
b111001010 #
0"
0$
#2295
b11110 %
b111001011 #
1"
1$
#2300
b111001100 #
0"
0$
#2305
b11111 %
b111001101 #
1"
1$
#2310
b111001110 #
0"
0$
#2315
b100000 %
b111001111 #
1"
1$
#2320
b111010000 #
0"
0$
#2325
b100001 %
b111010001 #
1"
1$
#2330
b111010010 #
0"
0$
#2335
b100010 %
b111010011 #
1"
1$
#2340
b111010100 #
0"
0$
#2345
b100011 %
b111010101 #
1"
1$
#2350
b111010110 #
0"
0$
#2355
b100100 %
b111010111 #
1"
1$
#2360
b111011000 #
0"
0$
#2365
b100101 %
b111011001 #
1"
1$
#2370
b111011010 #
0"
0$
#2375
b100110 %
b111011011 #
1"
1$
#2380
b111011100 #
0"
0$
#2385
b100111 %
b111011101 #
1"
1$
#2390
b111011110 #
0"
0$
#2395
b101000 %
b111011111 #
1"
1$
#2400
b111100000 #
0"
0$
#2405
b101001 %
b111100001 #
1"
1$
#2410
b111100010 #
0"
0$
#2415
b101010 %
b111100011 #
1"
1$
#2420
b111100100 #
0"
0$
#2425
b101011 %
b111100101 #
1"
1$
#2430
b111100110 #
0"
0$
#2435
b101100 %
b111100111 #
1"
1$
#2440
b111101000 #
0"
0$
#2445
b101101 %
b111101001 #
1"
1$
#2450
b111101010 #
0"
0$
#2455
b101110 %
b111101011 #
1"
1$
#2460
b111101100 #
0"
0$
#2465
b101111 %
b111101101 #
1"
1$
#2470
b111101110 #
0"
0$
#2475
b110000 %
b111101111 #
1"
1$
#2480
b111110000 #
0"
0$
#2485
b110001 %
b111110001 #
1"
1$
#2490
b111110010 #
0"
0$
#2495
1!
b110010 %
b111110011 #
1"
1$
#2500
b111110100 #
0"
0$
#2505
b110011 %
b111110101 #
1"
1$
#2510
b111110110 #
0"
0$
#2515
b110100 %
b111110111 #
1"
1$
#2520
b111111000 #
0"
0$
#2525
b110101 %
b111111001 #
1"
1$
#2530
b111111010 #
0"
0$
#2535
b110110 %
b111111011 #
1"
1$
#2540
b111111100 #
0"
0$
#2545
b110111 %
b111111101 #
1"
1$
#2550
b111111110 #
0"
0$
#2555
b111000 %
b111111111 #
1"
1$
#2560
b1000000000 #
0"
0$
#2565
b111001 %
b1000000001 #
1"
1$
#2570
b1000000010 #
0"
0$
#2575
b111010 %
b1000000011 #
1"
1$
#2580
b1000000100 #
0"
0$
#2585
b111011 %
b1000000101 #
1"
1$
#2590
b1000000110 #
0"
0$
#2595
b111100 %
b1000000111 #
1"
1$
#2600
b1000001000 #
0"
0$
#2605
b111101 %
b1000001001 #
1"
1$
#2610
b1000001010 #
0"
0$
#2615
b111110 %
b1000001011 #
1"
1$
#2620
b1000001100 #
0"
0$
#2625
b111111 %
b1000001101 #
1"
1$
#2630
b1000001110 #
0"
0$
#2635
b1000000 %
b1000001111 #
1"
1$
#2640
b1000010000 #
0"
0$
#2645
b1000001 %
b1000010001 #
1"
1$
#2650
b1000010010 #
0"
0$
#2655
b1000010 %
b1000010011 #
1"
1$
#2660
b1000010100 #
0"
0$
#2665
b1000011 %
b1000010101 #
1"
1$
#2670
b1000010110 #
0"
0$
#2675
b1000100 %
b1000010111 #
1"
1$
#2680
b1000011000 #
0"
0$
#2685
b1000101 %
b1000011001 #
1"
1$
#2690
b1000011010 #
0"
0$
#2695
b1000110 %
b1000011011 #
1"
1$
#2700
b1000011100 #
0"
0$
#2705
b1000111 %
b1000011101 #
1"
1$
#2710
b1000011110 #
0"
0$
#2715
b1001000 %
b1000011111 #
1"
1$
#2720
b1000100000 #
0"
0$
#2725
b1001001 %
b1000100001 #
1"
1$
#2730
b1000100010 #
0"
0$
#2735
b1001010 %
b1000100011 #
1"
1$
#2740
b1000100100 #
0"
0$
#2745
b1001011 %
b1000100101 #
1"
1$
#2750
b1000100110 #
0"
0$
#2755
b1001100 %
b1000100111 #
1"
1$
#2760
b1000101000 #
0"
0$
#2765
b1001101 %
b1000101001 #
1"
1$
#2770
b1000101010 #
0"
0$
#2775
b1001110 %
b1000101011 #
1"
1$
#2780
b1000101100 #
0"
0$
#2785
b1001111 %
b1000101101 #
1"
1$
#2790
b1000101110 #
0"
0$
#2795
b1010000 %
b1000101111 #
1"
1$
#2800
b1000110000 #
0"
0$
#2805
b1010001 %
b1000110001 #
1"
1$
#2810
b1000110010 #
0"
0$
#2815
b1010010 %
b1000110011 #
1"
1$
#2820
b1000110100 #
0"
0$
#2825
b1010011 %
b1000110101 #
1"
1$
#2830
b1000110110 #
0"
0$
#2835
b1010100 %
b1000110111 #
1"
1$
#2840
b1000111000 #
0"
0$
#2845
b1010101 %
b1000111001 #
1"
1$
#2850
b1000111010 #
0"
0$
#2855
b1010110 %
b1000111011 #
1"
1$
#2860
b1000111100 #
0"
0$
#2865
b1010111 %
b1000111101 #
1"
1$
#2870
b1000111110 #
0"
0$
#2875
b1011000 %
b1000111111 #
1"
1$
#2880
b1001000000 #
0"
0$
#2885
b1011001 %
b1001000001 #
1"
1$
#2890
b1001000010 #
0"
0$
#2895
b1011010 %
b1001000011 #
1"
1$
#2900
b1001000100 #
0"
0$
#2905
b1011011 %
b1001000101 #
1"
1$
#2910
b1001000110 #
0"
0$
#2915
b1011100 %
b1001000111 #
1"
1$
#2920
b1001001000 #
0"
0$
#2925
b1011101 %
b1001001001 #
1"
1$
#2930
b1001001010 #
0"
0$
#2935
b1011110 %
b1001001011 #
1"
1$
#2940
b1001001100 #
0"
0$
#2945
b1011111 %
b1001001101 #
1"
1$
#2950
b1001001110 #
0"
0$
#2955
b1100000 %
b1001001111 #
1"
1$
#2960
b1001010000 #
0"
0$
#2965
b1100001 %
b1001010001 #
1"
1$
#2970
b1001010010 #
0"
0$
#2975
b1100010 %
b1001010011 #
1"
1$
#2980
b1001010100 #
0"
0$
#2985
b1100011 %
b1001010101 #
1"
1$
#2990
b1001010110 #
0"
0$
#2995
0!
b0 %
b1001010111 #
1"
1$
#3000
b1001011000 #
0"
0$
#3005
b1 %
b1001011001 #
1"
1$
#3010
b1001011010 #
0"
0$
#3015
b10 %
b1001011011 #
1"
1$
#3020
b1001011100 #
0"
0$
#3025
b11 %
b1001011101 #
1"
1$
#3030
b1001011110 #
0"
0$
#3035
b100 %
b1001011111 #
1"
1$
#3040
b1001100000 #
0"
0$
#3045
b101 %
b1001100001 #
1"
1$
#3050
b1001100010 #
0"
0$
#3055
b110 %
b1001100011 #
1"
1$
#3060
b1001100100 #
0"
0$
#3065
b111 %
b1001100101 #
1"
1$
#3070
b1001100110 #
0"
0$
#3075
b1000 %
b1001100111 #
1"
1$
#3080
b1001101000 #
0"
0$
#3085
b1001 %
b1001101001 #
1"
1$
#3090
b1001101010 #
0"
0$
#3095
b1010 %
b1001101011 #
1"
1$
#3100
b1001101100 #
0"
0$
#3105
b1011 %
b1001101101 #
1"
1$
#3110
b1001101110 #
0"
0$
#3115
b1100 %
b1001101111 #
1"
1$
#3120
b1001110000 #
0"
0$
#3125
b1101 %
b1001110001 #
1"
1$
#3130
b1001110010 #
0"
0$
#3135
b1110 %
b1001110011 #
1"
1$
#3140
b1001110100 #
0"
0$
#3145
b1111 %
b1001110101 #
1"
1$
#3150
b1001110110 #
0"
0$
#3155
b10000 %
b1001110111 #
1"
1$
#3160
b1001111000 #
0"
0$
#3165
b10001 %
b1001111001 #
1"
1$
#3170
b1001111010 #
0"
0$
#3175
b10010 %
b1001111011 #
1"
1$
#3180
b1001111100 #
0"
0$
#3185
b10011 %
b1001111101 #
1"
1$
#3190
b1001111110 #
0"
0$
#3195
b10100 %
b1001111111 #
1"
1$
#3200
b1010000000 #
0"
0$
#3205
b10101 %
b1010000001 #
1"
1$
#3210
b1010000010 #
0"
0$
#3215
b10110 %
b1010000011 #
1"
1$
#3220
b1010000100 #
0"
0$
#3225
b10111 %
b1010000101 #
1"
1$
#3230
b1010000110 #
0"
0$
#3235
b11000 %
b1010000111 #
1"
1$
#3240
b1010001000 #
0"
0$
#3245
b11001 %
b1010001001 #
1"
1$
#3250
b1010001010 #
0"
0$
#3255
b11010 %
b1010001011 #
1"
1$
#3260
b1010001100 #
0"
0$
#3265
b11011 %
b1010001101 #
1"
1$
#3270
b1010001110 #
0"
0$
#3275
b11100 %
b1010001111 #
1"
1$
#3280
b1010010000 #
0"
0$
#3285
b11101 %
b1010010001 #
1"
1$
#3290
b1010010010 #
0"
0$
#3295
b11110 %
b1010010011 #
1"
1$
#3300
b1010010100 #
0"
0$
#3305
b11111 %
b1010010101 #
1"
1$
#3310
b1010010110 #
0"
0$
#3315
b100000 %
b1010010111 #
1"
1$
#3320
b1010011000 #
0"
0$
#3325
b100001 %
b1010011001 #
1"
1$
#3330
b1010011010 #
0"
0$
#3335
b100010 %
b1010011011 #
1"
1$
#3340
b1010011100 #
0"
0$
#3345
b100011 %
b1010011101 #
1"
1$
#3350
b1010011110 #
0"
0$
#3355
b100100 %
b1010011111 #
1"
1$
#3360
b1010100000 #
0"
0$
#3365
b100101 %
b1010100001 #
1"
1$
#3370
b1010100010 #
0"
0$
#3375
b100110 %
b1010100011 #
1"
1$
#3380
b1010100100 #
0"
0$
#3385
b100111 %
b1010100101 #
1"
1$
#3390
b1010100110 #
0"
0$
#3395
b101000 %
b1010100111 #
1"
1$
#3400
b1010101000 #
0"
0$
#3405
b101001 %
b1010101001 #
1"
1$
#3410
b1010101010 #
0"
0$
#3415
b101010 %
b1010101011 #
1"
1$
#3420
b1010101100 #
0"
0$
#3425
b101011 %
b1010101101 #
1"
1$
#3430
b1010101110 #
0"
0$
#3435
b101100 %
b1010101111 #
1"
1$
#3440
b1010110000 #
0"
0$
#3445
b101101 %
b1010110001 #
1"
1$
#3450
b1010110010 #
0"
0$
#3455
b101110 %
b1010110011 #
1"
1$
#3460
b1010110100 #
0"
0$
#3465
b101111 %
b1010110101 #
1"
1$
#3470
b1010110110 #
0"
0$
#3475
b110000 %
b1010110111 #
1"
1$
#3480
b1010111000 #
0"
0$
#3485
b110001 %
b1010111001 #
1"
1$
#3490
b1010111010 #
0"
0$
#3495
1!
b110010 %
b1010111011 #
1"
1$
#3500
b1010111100 #
0"
0$
#3505
b110011 %
b1010111101 #
1"
1$
#3510
b1010111110 #
0"
0$
#3515
b110100 %
b1010111111 #
1"
1$
#3520
b1011000000 #
0"
0$
#3525
b110101 %
b1011000001 #
1"
1$
