CONTROLE/latch/latch_SR.v
module latch_SR (S, R, Q);

	input S;
	input R;
	output reg Q;
    
    always @ (*) begin
		//se S e R forem iguais a 0 a saída será o Q anterior
        if (!S && !R) begin
            Q <= Q; 
        end

        else if (!S && R) begin 
            Q <= 1'b0; 
        end

        else if (S && !R) begin
            Q <= 1'b1;
        end 
    end
endmodule

CONTROLE/magnetron/magnetron_logic.v
module magnetron_logic (
    input wire startn, stopn, clearn, door_closed, timer_done, 
    output reg s, r);

    //obs: startn == 0, botão de ligar pressionado
    //stopn == 0, botão de pausar pressionado
    //clearn == 0, botão de limpar pressionado
    //door_closed == 0, porta está aberta
    //timer_done == 1, o cronômetro não está em operação

    always @ * begin
        //magnetron = 0 se a porta estiver aberta ou se stop, clear ou o timer estiverem ativos
        if (!door_closed || !stopn || !clearn || timer_done) 
            begin
                s <= 1'b0;
                r <= 1'b1;
            end
        //magnetron = 1 se start estiver ativo e a porta fechada
        else if (!startn && door_closed) 
            begin
                s <= 1'b1;
                r <= 1'b0;
            end
        else 
            begin  
                s <= 1'b0;
                r <= 1'b0;
            end
    end

endmodule

CONTROLE/magnetron_control.v

`include "magnetron/magnetron_logic.v"
`include "latch/latch_SR.v"


module magnetron_control (
    input wire startn, stopn, clearn, door_closed, timer_done, 
    output wire Q);

    wire s, r;

    magnetron_logic L1 (.startn(startn), 
                    .stopn(stopn),
                    .clearn(clearn),
                    .door_closed(door_closed),
                    .timer_done(timer_done),
                    .s(s), 
                    .r(r));
    
    
    latch_SR L2 (.S(s), 
                 .R(r),
                 .Q(Q)); 

endmodule

CONTROLE/magnetron_control_tb.v
`timescale 1us/1ps
`include "magnetron_control.v"

module magnetron_control_tb ();

    reg startn_TB, stopn_TB, clearn_TB, door_closed_TB, timer_done_TB;
    wire Q_TB;

      magnetron_control DUT(.Q(Q_TB),.startn(startn_TB),.stopn(stopn_TB),.clearn(clearn_TB),.door_closed(door_closed_TB),.timer_done(timer_done_TB));


    initial begin
        $dumpfile("magnetron_control_tb.vcd");
        $dumpvars(0,magnetron_control_tb);

      // simulação de funcionamento

      // no início, não há botões pressionados e a porta está aberta
          
        startn_TB = 1; stopn_TB = 1; clearn_TB = 1; door_closed_TB = 0; timer_done_TB = 1;

      // fecha-se a porta, rapidamente pressiona-se start e o timer é ativado
      #10 door_closed_TB = 1; startn_TB = 0; timer_done_TB = 0;

      #1 startn_TB = 1; // start solto

      #30 timer_done_TB = 1; // espera-se até que o timer termine a contágem

      // ------------------------------------------------------------------------------------------------

      // voltamos ao estado inicial
      #10 startn_TB = 1; stopn_TB = 1; clearn_TB = 1; door_closed_TB = 0; timer_done_TB = 1;

      // fecha-se a porta, rapidamente pressiona-se start e o timer é ativado
      #10 door_closed_TB = 1; startn_TB = 0; timer_done_TB = 0;

      #1 startn_TB = 1; // start solto

      // porta é aberta no meio da contágem
      #15 door_closed_TB = 0;

      // ------------------------------------------------------------------------------------------------

      // voltamos ao estado inicial
      #10 startn_TB = 1; stopn_TB = 1; clearn_TB = 1; door_closed_TB = 0; timer_done_TB = 1;

      // fecha-se a porta, rapidamente pressiona-se start e o timer é ativado
      #10 door_closed_TB = 1; startn_TB = 0; timer_done_TB = 0;

      #1 startn_TB = 1; // start solto

      //pausamos a contágem
      #15 stopn_TB = 0;
      #1 stopn_TB = 1;

      // ------------------------------------------------------------------------

      // voltamos ao estado inicial
      #10 startn_TB = 1; stopn_TB = 1; clearn_TB = 1; door_closed_TB = 0; timer_done_TB = 1;

      // fecha-se a porta, rapidamente pressiona-se start e o timer é ativado
      #10 door_closed_TB = 1; startn_TB = 0; timer_done_TB = 0;

      #1 startn_TB = 1; // start solto

      //clear pressionado
      #15 clearn_TB = 0;
      #1 clearn_TB = 1;

      // --------------------------------------------------------------------------

      // voltamos ao estado inicial
      #10 startn_TB = 1; stopn_TB = 1; clearn_TB = 1; door_closed_TB = 0; timer_done_TB = 1;

      // casos inválidos de tentativa de ligar  o magnetron "startn_TB = 1"
      #10 startn_TB = 0; stopn_TB = 0; clearn_TB = 0; door_closed_TB = 0; timer_done_TB = 0;
      #10 startn_TB = 0; stopn_TB = 0; clearn_TB = 0; door_closed_TB = 0; timer_done_TB = 1;
      #10 startn_TB = 0; stopn_TB = 0; clearn_TB = 0; door_closed_TB = 1; timer_done_TB = 0;
      #10 startn_TB = 0; stopn_TB = 0; clearn_TB = 0; door_closed_TB = 1; timer_done_TB = 1;
      #10 startn_TB = 0; stopn_TB = 0; clearn_TB = 1; door_closed_TB = 0; timer_done_TB = 0;
      #10 startn_TB = 0; stopn_TB = 0; clearn_TB = 1; door_closed_TB = 0; timer_done_TB = 1;
      #10 startn_TB = 0; stopn_TB = 0; clearn_TB = 1; door_closed_TB = 1; timer_done_TB = 0;
      #10 startn_TB = 0; stopn_TB = 0; clearn_TB = 1; door_closed_TB = 1; timer_done_TB = 1;
      #10 startn_TB = 0; stopn_TB = 1; clearn_TB = 0; door_closed_TB = 0; timer_done_TB = 0;
      #10 startn_TB = 0; stopn_TB = 1; clearn_TB = 0; door_closed_TB = 0; timer_done_TB = 1;
      #10 startn_TB = 0; stopn_TB = 1; clearn_TB = 0; door_closed_TB = 1; timer_done_TB = 0;
      #10 startn_TB = 0; stopn_TB = 1; clearn_TB = 0; door_closed_TB = 1; timer_done_TB = 1;
      #10 startn_TB = 0; stopn_TB = 1; clearn_TB = 1; door_closed_TB = 0; timer_done_TB = 0;
      #10 startn_TB = 0; stopn_TB = 1; clearn_TB = 1; door_closed_TB = 0; timer_done_TB = 1;
      #10 startn_TB = 0; stopn_TB = 1; clearn_TB = 1; door_closed_TB = 1; timer_done_TB = 1;
      
      #10;

    end 
endmodule

CONTROLE/magnetron_control_tb.vcd
$date
	Sun Dec 19 05:41:02 2021
$end
$version
	Icarus Verilog
$end
$timescale
	1ps
$end
$scope module magnetron_control_tb $end
$var wire 1 ! Q_TB $end
$var reg 1 " clearn_TB $end
$var reg 1 # door_closed_TB $end
$var reg 1 $ startn_TB $end
$var reg 1 % stopn_TB $end
$var reg 1 & timer_done_TB $end
$scope module DUT $end
$var wire 1 ! Q $end
$var wire 1 ' clearn $end
$var wire 1 ( door_closed $end
$var wire 1 ) r $end
$var wire 1 * s $end
$var wire 1 + startn $end
$var wire 1 , stopn $end
$var wire 1 - timer_done $end
$scope module L1 $end
$var wire 1 ' clearn $end
$var wire 1 ( door_closed $end
$var wire 1 + startn $end
$var wire 1 , stopn $end
$var wire 1 - timer_done $end
$var reg 1 . r $end
$var reg 1 / s $end
$upscope $end
$scope module L2 $end
$var wire 1 ) R $end
$var wire 1 * S $end
$var reg 1 0 Q $end
$upscope $end
$upscope $end
$upscope $end
$enddefinitions $end
#0
$dumpvars
00
0/
1.
1-
1,
1+
0*
1)
0(
1'
1&
1%
1$
0#
1"
0!
$end
#10000000
10
1!
0.
0)
1/
1*
0&
0-
0$
0+
1#
1(
#11000000
0/
0*
1$
1+
#41000000
00
0!
1.
1)
1&
1-
#51000000
0#
0(
#61000000
10
1!
0.
0)
1/
1*
0&
0-
0$
0+
1#
1(
#62000000
0/
0*
1$
1+
#77000000
00
0!
1.
1)
0#
0(
#87000000
1&
1-
#97000000
10
1!
0.
0)
1/
1*
0&
0-
0$
0+
1#
1(
#98000000
0/
0*
1$
1+
#113000000
00
0!
1.
1)
0%
0,
#114000000
0.
0)
1%
1,
#124000000
1.
1)
1&
1-
0#
0(
#134000000
10
1!
0.
0)
1/
1*
0&
0-
0$
0+
1#
1(
#135000000
0/
0*
1$
1+
#150000000
00
0!
1.
1)
0"
0'
#151000000
0.
0)
1"
1'
#161000000
1.
1)
1&
1-
0#
0(
#171000000
0&
0-
0"
0'
0%
0,
0$
0+
#181000000
1&
1-
#191000000
0&
0-
1#
1(
#201000000
1&
1-
#211000000
0&
0-
0#
0(
1"
1'
#221000000
1&
1-
#231000000
0&
0-
1#
1(
#241000000
1&
1-
#251000000
0&
0-
0#
0(
0"
0'
1%
1,
#261000000
1&
1-
#271000000
0&
0-
1#
1(
#281000000
1&
1-
#291000000
0&
0-
0#
0(
1"
1'
#301000000
1&
1-
#311000000
1#
1(
